<?xml version="1.0" encoding="UTF-8"?>
<qes:espresso xsi:schemaLocation="http://www.quantum-espresso.org/ns/qes/qes-1.0 http://www.quantum-espresso.org/ns/qes/qes_030920.xsd" Units="Hartree atomic units" xmlns:xsi="http://www.w3.org/2001/XMLSchema-instance" xmlns:qes="http://www.quantum-espresso.org/ns/qes/qes-1.0">
  <!--All quantities are in Hartree atomic units unless otherwise specified-->
  <general_info>
    <xml_format NAME="QEXSD" VERSION="20.04.20">QEXSD_20.04.20</xml_format>
    <creator NAME="PWSCF" VERSION="6.7MaX">XML file generated by PWSCF</creator>
    <created DATE="15Jan2021" TIME="14:18:58">This run was terminated on:  14:18:58  15 Jan 2021</created>
    <job>SnI4un</job>
  </general_info>
  <parallel_info>
    <nprocs>64</nprocs>
    <nthreads>1</nthreads>
    <ntasks>1</ntasks>
    <nbgrp>1</nbgrp>
    <npool>1</npool>
    <ndiag>64</ndiag>
  </parallel_info>
  <input>
    <control_variables>
      <title>SnI4un</title>
      <calculation>scf</calculation>
      <restart_mode>from_scratch</restart_mode>
      <prefix>SnI4un</prefix>
      <pseudo_dir>../../../pseudo/</pseudo_dir>
      <outdir>./out</outdir>
      <stress>true</stress>
      <forces>true</forces>
      <wf_collect>true</wf_collect>
      <disk_io>low</disk_io>
      <max_seconds>42500</max_seconds>
      <nstep>1</nstep>
      <etot_conv_thr>5.000000000000000e-8</etot_conv_thr>
      <forc_conv_thr>5.000000000000000e-4</forc_conv_thr>
      <press_conv_thr>5.000000000000000e-1</press_conv_thr>
      <verbosity>medium</verbosity>
      <print_every>100000</print_every>
    </control_variables>
    <atomic_species ntyp="2">
      <species name="Sn">
        <mass>1.187000000000000e2</mass>
        <pseudo_file>Sn.pbe-dn-kjpaw_psl.1.0.0.UPF</pseudo_file>
      </species>
      <species name="I">
        <mass>1.269000000000000e2</mass>
        <pseudo_file>I.pbe-n-kjpaw_psl.1.0.0.UPF</pseudo_file>
      </species>
    </atomic_species>
    <atomic_structure nat="5" alat="1.263551767203e1">
      <atomic_positions>
        <atom name="Sn" index="1">0.000000000000000e0 0.000000000000000e0 0.000000000000000e0</atom>
        <atom name="I" index="2">2.955485490040655e0 9.680032181988585e0 9.680032181988585e0</atom>
        <atom name="I" index="3">9.680032181988585e0 2.955485490040655e0 9.680032181988585e0</atom>
        <atom name="I" index="4">9.680032181988585e0 9.680032181988585e0 2.955485490040655e0</atom>
        <atom name="I" index="5">2.955485490040655e0 2.955485490040655e0 2.955485490040655e0</atom>
      </atomic_positions>
      <cell>
        <a1>1.263551767202924e1 0.000000000000000e0 0.000000000000000e0</a1>
        <a2>0.000000000000000e0 1.263551767202924e1 0.000000000000000e0</a2>
        <a3>0.000000000000000e0 0.000000000000000e0 1.263551767202924e1</a3>
      </cell>
    </atomic_structure>
    <dft>
      <functional>PBE</functional>
    </dft>
    <spin>
      <lsda>false</lsda>
      <noncolin>false</noncolin>
      <spinorbit>false</spinorbit>
    </spin>
    <bands>
      <nbnd>23</nbnd>
      <tot_charge>0.000000000000000e0</tot_charge>
      <occupations>fixed</occupations>
    </bands>
    <basis>
      <gamma_only>false</gamma_only>
      <ecutwfc>2.000000000000000e1</ecutwfc>
      <ecutrho>8.000000000000000e1</ecutrho>
    </basis>
    <electron_control>
      <diagonalization>davidson</diagonalization>
      <mixing_mode>plain</mixing_mode>
      <mixing_beta>7.000000000000000e-1</mixing_beta>
      <conv_thr>5.000000000000000e-7</conv_thr>
      <mixing_ndim>8</mixing_ndim>
      <max_nstep>100</max_nstep>
      <real_space_q>false</real_space_q>
      <real_space_beta>false</real_space_beta>
      <tq_smoothing>false</tq_smoothing>
      <tbeta_smoothing>false</tbeta_smoothing>
      <diago_thr_init>0.000000000000000e0</diago_thr_init>
      <diago_full_acc>false</diago_full_acc>
      <diago_cg_maxiter>20</diago_cg_maxiter>
      <diago_ppcg_maxiter>20</diago_ppcg_maxiter>
    </electron_control>
    <k_points_IBZ>
      <monkhorst_pack nk1="2" nk2="2" nk3="2" k1="0" k2="0" k3="0">Monkhorst-Pack</monkhorst_pack>
    </k_points_IBZ>
    <ion_control>
      <ion_dynamics>none</ion_dynamics>
      <upscale>1.000000000000000e2</upscale>
      <remove_rigid_rot>false</remove_rigid_rot>
      <refold_pos>false</refold_pos>
    </ion_control>
    <cell_control>
      <cell_dynamics>none</cell_dynamics>
      <pressure>0.000000000000000e0</pressure>
      <wmass>6.263000000000000e2</wmass>
      <cell_factor>0.000000000000000e0</cell_factor>
      <fix_volume>false</fix_volume>
      <fix_area>false</fix_area>
      <isotropic>false</isotropic>
    </cell_control>
    <symmetry_flags>
      <nosym>false</nosym>
      <nosym_evc>false</nosym_evc>
      <noinv>false</noinv>
      <no_t_rev>false</no_t_rev>
      <force_symmorphic>false</force_symmorphic>
      <use_all_frac>false</use_all_frac>
    </symmetry_flags>
  </input>
  <output>
    <convergence_info>
      <scf_conv>
        <convergence_achieved>true</convergence_achieved>
        <n_scf_steps>6</n_scf_steps>
        <scf_error>1.502121047762851e-7</scf_error>
      </scf_conv>
    </convergence_info>
    <algorithmic_info>
      <real_space_q>false</real_space_q>
      <real_space_beta>false</real_space_beta>
      <uspp>true</uspp>
      <paw>true</paw>
    </algorithmic_info>
    <atomic_species ntyp="2" pseudo_dir="../../../pseudo/">
      <species name="Sn">
        <mass>1.187000000000000e2</mass>
        <pseudo_file>Sn.pbe-dn-kjpaw_psl.1.0.0.UPF</pseudo_file>
      </species>
      <species name="I">
        <mass>1.269000000000000e2</mass>
        <pseudo_file>I.pbe-n-kjpaw_psl.1.0.0.UPF</pseudo_file>
      </species>
    </atomic_species>
    <atomic_structure nat="5" alat="1.263551767203e1">
      <atomic_positions>
        <atom name="Sn" index="1">0.000000000000000e0 0.000000000000000e0 0.000000000000000e0</atom>
        <atom name="I" index="2">2.955485490040655e0 9.680032181988585e0 9.680032181988585e0</atom>
        <atom name="I" index="3">9.680032181988585e0 2.955485490040655e0 9.680032181988585e0</atom>
        <atom name="I" index="4">9.680032181988585e0 9.680032181988585e0 2.955485490040655e0</atom>
        <atom name="I" index="5">2.955485490040655e0 2.955485490040655e0 2.955485490040655e0</atom>
      </atomic_positions>
      <cell>
        <a1>1.263551767202924e1 0.000000000000000e0 0.000000000000000e0</a1>
        <a2>0.000000000000000e0 1.263551767202924e1 0.000000000000000e0</a2>
        <a3>0.000000000000000e0 0.000000000000000e0 1.263551767202924e1</a3>
      </cell>
    </atomic_structure>
    <symmetries>
      <nsym>24</nsym>
      <nrot>48</nrot>
      <space_group>0</space_group>
      <symmetry>
        <info name="identity" class="not found">crystal_symmetry</info>
        <rotation rank="2" dims="3 3" order="F">
          1.000000000000000e0 0.000000000000000e0 0.000000000000000e0
          0.000000000000000e0 1.000000000000000e0 0.000000000000000e0
          0.000000000000000e0 0.000000000000000e0 1.000000000000000e0
          </rotation>
        <fractional_translation>0.000000000000000e0 0.000000000000000e0 0.000000000000000e0</fractional_translation>
        <equivalent_atoms nat="5" size="5">
          1 2 3 4 5
          </equivalent_atoms>
      </symmetry>
      <symmetry>
        <info name="180 deg rotation - cart. axis [0,0,1]" class="not found">crystal_symmetry</info>
        <rotation rank="2" dims="3 3" order="F">
          -1.000000000000000e0 0.000000000000000e0 0.000000000000000e0
          0.000000000000000e0 -1.000000000000000e0 0.000000000000000e0
          0.000000000000000e0 0.000000000000000e0 1.000000000000000e0
          </rotation>
        <fractional_translation>0.000000000000000e0 0.000000000000000e0 0.000000000000000e0</fractional_translation>
        <equivalent_atoms nat="5" size="5">
          1 3 2 5 4
          </equivalent_atoms>
      </symmetry>
      <symmetry>
        <info name="180 deg rotation - cart. axis [0,1,0]" class="not found">crystal_symmetry</info>
        <rotation rank="2" dims="3 3" order="F">
          -1.000000000000000e0 0.000000000000000e0 0.000000000000000e0
          0.000000000000000e0 1.000000000000000e0 0.000000000000000e0
          0.000000000000000e0 0.000000000000000e0 -1.000000000000000e0
          </rotation>
        <fractional_translation>0.000000000000000e0 0.000000000000000e0 0.000000000000000e0</fractional_translation>
        <equivalent_atoms nat="5" size="5">
          1 4 5 2 3
          </equivalent_atoms>
      </symmetry>
      <symmetry>
        <info name="180 deg rotation - cart. axis [1,0,0]" class="not found">crystal_symmetry</info>
        <rotation rank="2" dims="3 3" order="F">
          1.000000000000000e0 0.000000000000000e0 0.000000000000000e0
          0.000000000000000e0 -1.000000000000000e0 0.000000000000000e0
          0.000000000000000e0 0.000000000000000e0 -1.000000000000000e0
          </rotation>
        <fractional_translation>0.000000000000000e0 0.000000000000000e0 0.000000000000000e0</fractional_translation>
        <equivalent_atoms nat="5" size="5">
          1 5 4 3 2
          </equivalent_atoms>
      </symmetry>
      <symmetry>
        <info name="120 deg rotation - cart. axis [-1,-1,-1]" class="not found">crystal_symmetry</info>
        <rotation rank="2" dims="3 3" order="F">
          0.000000000000000e0 1.000000000000000e0 0.000000000000000e0
          0.000000000000000e0 0.000000000000000e0 1.000000000000000e0
          1.000000000000000e0 0.000000000000000e0 0.000000000000000e0
          </rotation>
        <fractional_translation>0.000000000000000e0 0.000000000000000e0 0.000000000000000e0</fractional_translation>
        <equivalent_atoms nat="5" size="5">
          1 4 2 3 5
          </equivalent_atoms>
      </symmetry>
      <symmetry>
        <info name="120 deg rotation - cart. axis [-1,1,1]" class="not found">crystal_symmetry</info>
        <rotation rank="2" dims="3 3" order="F">
          0.000000000000000e0 -1.000000000000000e0 0.000000000000000e0
          0.000000000000000e0 0.000000000000000e0 1.000000000000000e0
          -1.000000000000000e0 0.000000000000000e0 0.000000000000000e0
          </rotation>
        <fractional_translation>0.000000000000000e0 0.000000000000000e0 0.000000000000000e0</fractional_translation>
        <equivalent_atoms nat="5" size="5">
          1 2 4 5 3
          </equivalent_atoms>
      </symmetry>
      <symmetry>
        <info name="120 deg rotation - cart. axis [1,1,-1]" class="not found">crystal_symmetry</info>
        <rotation rank="2" dims="3 3" order="F">
          0.000000000000000e0 1.000000000000000e0 0.000000000000000e0
          0.000000000000000e0 0.000000000000000e0 -1.000000000000000e0
          -1.000000000000000e0 0.000000000000000e0 0.000000000000000e0
          </rotation>
        <fractional_translation>0.000000000000000e0 0.000000000000000e0 0.000000000000000e0</fractional_translation>
        <equivalent_atoms nat="5" size="5">
          1 3 5 4 2
          </equivalent_atoms>
      </symmetry>
      <symmetry>
        <info name="120 deg rotation - cart. axis [1,-1,1]" class="not found">crystal_symmetry</info>
        <rotation rank="2" dims="3 3" order="F">
          0.000000000000000e0 -1.000000000000000e0 0.000000000000000e0
          0.000000000000000e0 0.000000000000000e0 -1.000000000000000e0
          1.000000000000000e0 0.000000000000000e0 0.000000000000000e0
          </rotation>
        <fractional_translation>0.000000000000000e0 0.000000000000000e0 0.000000000000000e0</fractional_translation>
        <equivalent_atoms nat="5" size="5">
          1 5 3 2 4
          </equivalent_atoms>
      </symmetry>
      <symmetry>
        <info name="120 deg rotation - cart. axis [1,1,1]" class="not found">crystal_symmetry</info>
        <rotation rank="2" dims="3 3" order="F">
          0.000000000000000e0 0.000000000000000e0 1.000000000000000e0
          1.000000000000000e0 0.000000000000000e0 0.000000000000000e0
          0.000000000000000e0 1.000000000000000e0 0.000000000000000e0
          </rotation>
        <fractional_translation>0.000000000000000e0 0.000000000000000e0 0.000000000000000e0</fractional_translation>
        <equivalent_atoms nat="5" size="5">
          1 3 4 2 5
          </equivalent_atoms>
      </symmetry>
      <symmetry>
        <info name="120 deg rotation - cart. axis [-1,1,-1]" class="not found">crystal_symmetry</info>
        <rotation rank="2" dims="3 3" order="F">
          0.000000000000000e0 0.000000000000000e0 1.000000000000000e0
          -1.000000000000000e0 0.000000000000000e0 0.000000000000000e0
          0.000000000000000e0 -1.000000000000000e0 0.000000000000000e0
          </rotation>
        <fractional_translation>0.000000000000000e0 0.000000000000000e0 0.000000000000000e0</fractional_translation>
        <equivalent_atoms nat="5" size="5">
          1 4 3 5 2
          </equivalent_atoms>
      </symmetry>
      <symmetry>
        <info name="120 deg rotation - cart. axis [1,-1,-1]" class="not found">crystal_symmetry</info>
        <rotation rank="2" dims="3 3" order="F">
          0.000000000000000e0 0.000000000000000e0 -1.000000000000000e0
          -1.000000000000000e0 0.000000000000000e0 0.000000000000000e0
          0.000000000000000e0 1.000000000000000e0 0.000000000000000e0
          </rotation>
        <fractional_translation>0.000000000000000e0 0.000000000000000e0 0.000000000000000e0</fractional_translation>
        <equivalent_atoms nat="5" size="5">
          1 2 5 3 4
          </equivalent_atoms>
      </symmetry>
      <symmetry>
        <info name="120 deg rotation - cart. axis [-1,-1,1]" class="not found">crystal_symmetry</info>
        <rotation rank="2" dims="3 3" order="F">
          0.000000000000000e0 0.000000000000000e0 -1.000000000000000e0
          1.000000000000000e0 0.000000000000000e0 0.000000000000000e0
          0.000000000000000e0 -1.000000000000000e0 0.000000000000000e0
          </rotation>
        <fractional_translation>0.000000000000000e0 0.000000000000000e0 0.000000000000000e0</fractional_translation>
        <equivalent_atoms nat="5" size="5">
          1 5 2 4 3
          </equivalent_atoms>
      </symmetry>
      <symmetry>
        <info name="inv. 180 deg rotation - cart. axis [1,1,0]" class="not found">crystal_symmetry</info>
        <rotation rank="2" dims="3 3" order="F">
          0.000000000000000e0 -1.000000000000000e0 0.000000000000000e0
          -1.000000000000000e0 0.000000000000000e0 0.000000000000000e0
          0.000000000000000e0 0.000000000000000e0 1.000000000000000e0
          </rotation>
        <fractional_translation>0.000000000000000e0 0.000000000000000e0 0.000000000000000e0</fractional_translation>
        <equivalent_atoms nat="5" size="5">
          1 2 3 5 4
          </equivalent_atoms>
      </symmetry>
      <symmetry>
        <info name="inv. 180 deg rotation - cart. axis [1,-1,0]" class="not found">crystal_symmetry</info>
        <rotation rank="2" dims="3 3" order="F">
          0.000000000000000e0 1.000000000000000e0 0.000000000000000e0
          1.000000000000000e0 0.000000000000000e0 0.000000000000000e0
          0.000000000000000e0 0.000000000000000e0 1.000000000000000e0
          </rotation>
        <fractional_translation>0.000000000000000e0 0.000000000000000e0 0.000000000000000e0</fractional_translation>
        <equivalent_atoms nat="5" size="5">
          1 3 2 4 5
          </equivalent_atoms>
      </symmetry>
      <symmetry>
        <info name="inv.  90 deg rotation - cart. axis [0,0,-1]" class="not found">crystal_symmetry</info>
        <rotation rank="2" dims="3 3" order="F">
          0.000000000000000e0 -1.000000000000000e0 0.000000000000000e0
          1.000000000000000e0 0.000000000000000e0 0.000000000000000e0
          0.000000000000000e0 0.000000000000000e0 -1.000000000000000e0
          </rotation>
        <fractional_translation>0.000000000000000e0 0.000000000000000e0 0.000000000000000e0</fractional_translation>
        <equivalent_atoms nat="5" size="5">
          1 5 4 2 3
          </equivalent_atoms>
      </symmetry>
      <symmetry>
        <info name="inv.  90 deg rotation - cart. axis [0,0,1]" class="not found">crystal_symmetry</info>
        <rotation rank="2" dims="3 3" order="F">
          0.000000000000000e0 1.000000000000000e0 0.000000000000000e0
          -1.000000000000000e0 0.000000000000000e0 0.000000000000000e0
          0.000000000000000e0 0.000000000000000e0 -1.000000000000000e0
          </rotation>
        <fractional_translation>0.000000000000000e0 0.000000000000000e0 0.000000000000000e0</fractional_translation>
        <equivalent_atoms nat="5" size="5">
          1 4 5 3 2
          </equivalent_atoms>
      </symmetry>
      <symmetry>
        <info name="inv. 180 deg rotation - cart. axis [1,0,1]" class="not found">crystal_symmetry</info>
        <rotation rank="2" dims="3 3" order="F">
          0.000000000000000e0 0.000000000000000e0 -1.000000000000000e0
          0.000000000000000e0 1.000000000000000e0 0.000000000000000e0
          -1.000000000000000e0 0.000000000000000e0 0.000000000000000e0
          </rotation>
        <fractional_translation>0.000000000000000e0 0.000000000000000e0 0.000000000000000e0</fractional_translation>
        <equivalent_atoms nat="5" size="5">
          1 2 5 4 3
          </equivalent_atoms>
      </symmetry>
      <symmetry>
        <info name="inv. 180 deg rotation - cart. axis [-1,0,1]" class="not found">crystal_symmetry</info>
        <rotation rank="2" dims="3 3" order="F">
          0.000000000000000e0 0.000000000000000e0 1.000000000000000e0
          0.000000000000000e0 1.000000000000000e0 0.000000000000000e0
          1.000000000000000e0 0.000000000000000e0 0.000000000000000e0
          </rotation>
        <fractional_translation>0.000000000000000e0 0.000000000000000e0 0.000000000000000e0</fractional_translation>
        <equivalent_atoms nat="5" size="5">
          1 4 3 2 5
          </equivalent_atoms>
      </symmetry>
      <symmetry>
        <info name="inv.  90 deg rotation - cart. axis [0,1,0]" class="not found">crystal_symmetry</info>
        <rotation rank="2" dims="3 3" order="F">
          0.000000000000000e0 0.000000000000000e0 -1.000000000000000e0
          0.000000000000000e0 -1.000000000000000e0 0.000000000000000e0
          1.000000000000000e0 0.000000000000000e0 0.000000000000000e0
          </rotation>
        <fractional_translation>0.000000000000000e0 0.000000000000000e0 0.000000000000000e0</fractional_translation>
        <equivalent_atoms nat="5" size="5">
          1 5 2 3 4
          </equivalent_atoms>
      </symmetry>
      <symmetry>
        <info name="inv.  90 deg rotation - cart. axis [0,-1,0]" class="not found">crystal_symmetry</info>
        <rotation rank="2" dims="3 3" order="F">
          0.000000000000000e0 0.000000000000000e0 1.000000000000000e0
          0.000000000000000e0 -1.000000000000000e0 0.000000000000000e0
          -1.000000000000000e0 0.000000000000000e0 0.000000000000000e0
          </rotation>
        <fractional_translation>0.000000000000000e0 0.000000000000000e0 0.000000000000000e0</fractional_translation>
        <equivalent_atoms nat="5" size="5">
          1 3 4 5 2
          </equivalent_atoms>
      </symmetry>
      <symmetry>
        <info name="inv. 180 deg rotation - cart. axis [0,1,1]" class="not found">crystal_symmetry</info>
        <rotation rank="2" dims="3 3" order="F">
          1.000000000000000e0 0.000000000000000e0 0.000000000000000e0
          0.000000000000000e0 0.000000000000000e0 -1.000000000000000e0
          0.000000000000000e0 -1.000000000000000e0 0.000000000000000e0
          </rotation>
        <fractional_translation>0.000000000000000e0 0.000000000000000e0 0.000000000000000e0</fractional_translation>
        <equivalent_atoms nat="5" size="5">
          1 5 3 4 2
          </equivalent_atoms>
      </symmetry>
      <symmetry>
        <info name="inv. 180 deg rotation - cart. axis [0,1,-1]" class="not found">crystal_symmetry</info>
        <rotation rank="2" dims="3 3" order="F">
          1.000000000000000e0 0.000000000000000e0 0.000000000000000e0
          0.000000000000000e0 0.000000000000000e0 1.000000000000000e0
          0.000000000000000e0 1.000000000000000e0 0.000000000000000e0
          </rotation>
        <fractional_translation>0.000000000000000e0 0.000000000000000e0 0.000000000000000e0</fractional_translation>
        <equivalent_atoms nat="5" size="5">
          1 2 4 3 5
          </equivalent_atoms>
      </symmetry>
      <symmetry>
        <info name="inv.  90 deg rotation - cart. axis [-1,0,0]" class="not found">crystal_symmetry</info>
        <rotation rank="2" dims="3 3" order="F">
          -1.000000000000000e0 0.000000000000000e0 0.000000000000000e0
          0.000000000000000e0 0.000000000000000e0 -1.000000000000000e0
          0.000000000000000e0 1.000000000000000e0 0.000000000000000e0
          </rotation>
        <fractional_translation>0.000000000000000e0 0.000000000000000e0 0.000000000000000e0</fractional_translation>
        <equivalent_atoms nat="5" size="5">
          1 3 5 2 4
          </equivalent_atoms>
      </symmetry>
      <symmetry>
        <info name="inv.  90 deg rotation - cart. axis [1,0,0]" class="not found">crystal_symmetry</info>
        <rotation rank="2" dims="3 3" order="F">
          -1.000000000000000e0 0.000000000000000e0 0.000000000000000e0
          0.000000000000000e0 0.000000000000000e0 1.000000000000000e0
          0.000000000000000e0 -1.000000000000000e0 0.000000000000000e0
          </rotation>
        <fractional_translation>0.000000000000000e0 0.000000000000000e0 0.000000000000000e0</fractional_translation>
        <equivalent_atoms nat="5" size="5">
          1 4 2 5 3
          </equivalent_atoms>
      </symmetry>
      <symmetry>
        <info name="inversion" class="not found">lattice_symmetry</info>
        <rotation rank="2" dims="3 3" order="F">
          -1.000000000000000e0 0.000000000000000e0 0.000000000000000e0
          0.000000000000000e0 -1.000000000000000e0 0.000000000000000e0
          0.000000000000000e0 0.000000000000000e0 -1.000000000000000e0
          </rotation>
      </symmetry>
      <symmetry>
        <info name="inv. 180 deg rotation - cart. axis [0,0,1]" class="not found">lattice_symmetry</info>
        <rotation rank="2" dims="3 3" order="F">
          1.000000000000000e0 0.000000000000000e0 0.000000000000000e0
          0.000000000000000e0 1.000000000000000e0 0.000000000000000e0
          0.000000000000000e0 0.000000000000000e0 -1.000000000000000e0
          </rotation>
      </symmetry>
      <symmetry>
        <info name="inv. 180 deg rotation - cart. axis [0,1,0]" class="not found">lattice_symmetry</info>
        <rotation rank="2" dims="3 3" order="F">
          1.000000000000000e0 0.000000000000000e0 0.000000000000000e0
          0.000000000000000e0 -1.000000000000000e0 0.000000000000000e0
          0.000000000000000e0 0.000000000000000e0 1.000000000000000e0
          </rotation>
      </symmetry>
      <symmetry>
        <info name="inv. 180 deg rotation - cart. axis [1,0,0]" class="not found">lattice_symmetry</info>
        <rotation rank="2" dims="3 3" order="F">
          -1.000000000000000e0 0.000000000000000e0 0.000000000000000e0
          0.000000000000000e0 1.000000000000000e0 0.000000000000000e0
          0.000000000000000e0 0.000000000000000e0 1.000000000000000e0
          </rotation>
      </symmetry>
      <symmetry>
        <info name="180 deg rotation - cart. axis [0,1,1]" class="not found">lattice_symmetry</info>
        <rotation rank="2" dims="3 3" order="F">
          -1.000000000000000e0 0.000000000000000e0 0.000000000000000e0
          0.000000000000000e0 0.000000000000000e0 1.000000000000000e0
          0.000000000000000e0 1.000000000000000e0 0.000000000000000e0
          </rotation>
      </symmetry>
      <symmetry>
        <info name="180 deg rotation - cart. axis [0,1,-1]" class="not found">lattice_symmetry</info>
        <rotation rank="2" dims="3 3" order="F">
          -1.000000000000000e0 0.000000000000000e0 0.000000000000000e0
          0.000000000000000e0 0.000000000000000e0 -1.000000000000000e0
          0.000000000000000e0 -1.000000000000000e0 0.000000000000000e0
          </rotation>
      </symmetry>
      <symmetry>
        <info name=" 90 deg rotation - cart. axis [-1,0,0]" class="not found">lattice_symmetry</info>
        <rotation rank="2" dims="3 3" order="F">
          1.000000000000000e0 0.000000000000000e0 0.000000000000000e0
          0.000000000000000e0 0.000000000000000e0 1.000000000000000e0
          0.000000000000000e0 -1.000000000000000e0 0.000000000000000e0
          </rotation>
      </symmetry>
      <symmetry>
        <info name=" 90 deg rotation - cart. axis [1,0,0]" class="not found">lattice_symmetry</info>
        <rotation rank="2" dims="3 3" order="F">
          1.000000000000000e0 0.000000000000000e0 0.000000000000000e0
          0.000000000000000e0 0.000000000000000e0 -1.000000000000000e0
          0.000000000000000e0 1.000000000000000e0 0.000000000000000e0
          </rotation>
      </symmetry>
      <symmetry>
        <info name="180 deg rotation - cart. axis [1,1,0]" class="not found">lattice_symmetry</info>
        <rotation rank="2" dims="3 3" order="F">
          0.000000000000000e0 1.000000000000000e0 0.000000000000000e0
          1.000000000000000e0 0.000000000000000e0 0.000000000000000e0
          0.000000000000000e0 0.000000000000000e0 -1.000000000000000e0
          </rotation>
      </symmetry>
      <symmetry>
        <info name="180 deg rotation - cart. axis [1,-1,0]" class="not found">lattice_symmetry</info>
        <rotation rank="2" dims="3 3" order="F">
          0.000000000000000e0 -1.000000000000000e0 0.000000000000000e0
          -1.000000000000000e0 0.000000000000000e0 0.000000000000000e0
          0.000000000000000e0 0.000000000000000e0 -1.000000000000000e0
          </rotation>
      </symmetry>
      <symmetry>
        <info name=" 90 deg rotation - cart. axis [0,0,-1]" class="not found">lattice_symmetry</info>
        <rotation rank="2" dims="3 3" order="F">
          0.000000000000000e0 1.000000000000000e0 0.000000000000000e0
          -1.000000000000000e0 0.000000000000000e0 0.000000000000000e0
          0.000000000000000e0 0.000000000000000e0 1.000000000000000e0
          </rotation>
      </symmetry>
      <symmetry>
        <info name=" 90 deg rotation - cart. axis [0,0,1]" class="not found">lattice_symmetry</info>
        <rotation rank="2" dims="3 3" order="F">
          0.000000000000000e0 -1.000000000000000e0 0.000000000000000e0
          1.000000000000000e0 0.000000000000000e0 0.000000000000000e0
          0.000000000000000e0 0.000000000000000e0 1.000000000000000e0
          </rotation>
      </symmetry>
      <symmetry>
        <info name="180 deg rotation - cart. axis [1,0,1]" class="not found">lattice_symmetry</info>
        <rotation rank="2" dims="3 3" order="F">
          0.000000000000000e0 0.000000000000000e0 1.000000000000000e0
          0.000000000000000e0 -1.000000000000000e0 0.000000000000000e0
          1.000000000000000e0 0.000000000000000e0 0.000000000000000e0
          </rotation>
      </symmetry>
      <symmetry>
        <info name="180 deg rotation - cart. axis [-1,0,1]" class="not found">lattice_symmetry</info>
        <rotation rank="2" dims="3 3" order="F">
          0.000000000000000e0 0.000000000000000e0 -1.000000000000000e0
          0.000000000000000e0 -1.000000000000000e0 0.000000000000000e0
          -1.000000000000000e0 0.000000000000000e0 0.000000000000000e0
          </rotation>
      </symmetry>
      <symmetry>
        <info name=" 90 deg rotation - cart. axis [0,1,0]" class="not found">lattice_symmetry</info>
        <rotation rank="2" dims="3 3" order="F">
          0.000000000000000e0 0.000000000000000e0 1.000000000000000e0
          0.000000000000000e0 1.000000000000000e0 0.000000000000000e0
          -1.000000000000000e0 0.000000000000000e0 0.000000000000000e0
          </rotation>
      </symmetry>
      <symmetry>
        <info name=" 90 deg rotation - cart. axis [0,-1,0]" class="not found">lattice_symmetry</info>
        <rotation rank="2" dims="3 3" order="F">
          0.000000000000000e0 0.000000000000000e0 -1.000000000000000e0
          0.000000000000000e0 1.000000000000000e0 0.000000000000000e0
          1.000000000000000e0 0.000000000000000e0 0.000000000000000e0
          </rotation>
      </symmetry>
      <symmetry>
        <info name="inv. 120 deg rotation - cart. axis [-1,-1,-1]" class="not found">lattice_symmetry</info>
        <rotation rank="2" dims="3 3" order="F">
          0.000000000000000e0 -1.000000000000000e0 0.000000000000000e0
          0.000000000000000e0 0.000000000000000e0 -1.000000000000000e0
          -1.000000000000000e0 0.000000000000000e0 0.000000000000000e0
          </rotation>
      </symmetry>
      <symmetry>
        <info name="inv. 120 deg rotation - cart. axis [-1,1,1]" class="not found">lattice_symmetry</info>
        <rotation rank="2" dims="3 3" order="F">
          0.000000000000000e0 1.000000000000000e0 0.000000000000000e0
          0.000000000000000e0 0.000000000000000e0 -1.000000000000000e0
          1.000000000000000e0 0.000000000000000e0 0.000000000000000e0
          </rotation>
      </symmetry>
      <symmetry>
        <info name="inv. 120 deg rotation - cart. axis [1,1,-1]" class="not found">lattice_symmetry</info>
        <rotation rank="2" dims="3 3" order="F">
          0.000000000000000e0 -1.000000000000000e0 0.000000000000000e0
          0.000000000000000e0 0.000000000000000e0 1.000000000000000e0
          1.000000000000000e0 0.000000000000000e0 0.000000000000000e0
          </rotation>
      </symmetry>
      <symmetry>
        <info name="inv. 120 deg rotation - cart. axis [1,-1,1]" class="not found">lattice_symmetry</info>
        <rotation rank="2" dims="3 3" order="F">
          0.000000000000000e0 1.000000000000000e0 0.000000000000000e0
          0.000000000000000e0 0.000000000000000e0 1.000000000000000e0
          -1.000000000000000e0 0.000000000000000e0 0.000000000000000e0
          </rotation>
      </symmetry>
      <symmetry>
        <info name="inv. 120 deg rotation - cart. axis [1,1,1]" class="not found">lattice_symmetry</info>
        <rotation rank="2" dims="3 3" order="F">
          0.000000000000000e0 0.000000000000000e0 -1.000000000000000e0
          -1.000000000000000e0 0.000000000000000e0 0.000000000000000e0
          0.000000000000000e0 -1.000000000000000e0 0.000000000000000e0
          </rotation>
      </symmetry>
      <symmetry>
        <info name="inv. 120 deg rotation - cart. axis [-1,1,-1]" class="not found">lattice_symmetry</info>
        <rotation rank="2" dims="3 3" order="F">
          0.000000000000000e0 0.000000000000000e0 -1.000000000000000e0
          1.000000000000000e0 0.000000000000000e0 0.000000000000000e0
          0.000000000000000e0 1.000000000000000e0 0.000000000000000e0
          </rotation>
      </symmetry>
      <symmetry>
        <info name="inv. 120 deg rotation - cart. axis [1,-1,-1]" class="not found">lattice_symmetry</info>
        <rotation rank="2" dims="3 3" order="F">
          0.000000000000000e0 0.000000000000000e0 1.000000000000000e0
          1.000000000000000e0 0.000000000000000e0 0.000000000000000e0
          0.000000000000000e0 -1.000000000000000e0 0.000000000000000e0
          </rotation>
      </symmetry>
      <symmetry>
        <info name="inv. 120 deg rotation - cart. axis [-1,-1,1]" class="not found">lattice_symmetry</info>
        <rotation rank="2" dims="3 3" order="F">
          0.000000000000000e0 0.000000000000000e0 1.000000000000000e0
          -1.000000000000000e0 0.000000000000000e0 0.000000000000000e0
          0.000000000000000e0 1.000000000000000e0 0.000000000000000e0
          </rotation>
      </symmetry>
    </symmetries>
    <basis_set>
      <gamma_only>false</gamma_only>
      <ecutwfc>2.000000000000000e1</ecutwfc>
      <ecutrho>8.000000000000000e1</ecutrho>
      <fft_grid nr1="54" nr2="54" nr3="54"></fft_grid>
      <fft_smooth nr1="54" nr2="54" nr3="54"></fft_smooth>
      <fft_box nr1="54" nr2="54" nr3="54"></fft_box>
      <ngm>68891</ngm>
      <ngms>68891</ngms>
      <npwx>8642</npwx>
      <reciprocal_lattice>
        <b1>1.000000000000000e0 0.000000000000000e0 0.000000000000000e0</b1>
        <b2>0.000000000000000e0 1.000000000000000e0 0.000000000000000e0</b2>
        <b3>0.000000000000000e0 0.000000000000000e0 1.000000000000000e0</b3>
      </reciprocal_lattice>
    </basis_set>
    <dft>
      <functional>PBE</functional>
    </dft>
    <magnetization>
      <lsda>false</lsda>
      <noncolin>false</noncolin>
      <spinorbit>false</spinorbit>
      <total>0.000000000000000e0</total>
      <absolute>0.000000000000000e0</absolute>
    </magnetization>
    <total_energy>
      <etot>-9.789075228178882e2</etot>
      <eband>-1.252214779171783e1</eband>
      <ehart>4.735913321520477e1</ehart>
      <vtxc>-2.680291724919105e1</vtxc>
      <etxc>-5.549359915790723e1</etxc>
      <ewald>-5.971649898865838e1</ewald>
    </total_energy>
    <band_structure>
      <lsda>false</lsda>
      <noncolin>false</noncolin>
      <spinorbit>false</spinorbit>
      <nbnd>23</nbnd>
      <nelec>4.200000000000000e1</nelec>
      <num_of_atomic_wfc>25</num_of_atomic_wfc>
      <wf_collected>true</wf_collected>
      <fermi_energy>-4.165939268913466e-3</fermi_energy>
      <highestOccupiedLevel>-4.165939268913466e-3</highestOccupiedLevel>
      <lowestUnoccupiedLevel>5.051018232559548e-2</lowestUnoccupiedLevel>
      <starting_k_points>
        <monkhorst_pack nk1="2" nk2="2" nk3="2" k1="0" k2="0" k3="0">Monkhorst-Pack</monkhorst_pack>
      </starting_k_points>
      <nks>4</nks>
      <occupations_kind>fixed</occupations_kind>
      <ks_energies>
        <k_point weight="2.500000000000e-1">0.000000000000000e0 0.000000000000000e0 0.000000000000000e0</k_point>
        <npw>8601</npw>
        <eigenvalues size="23">
          -7.830458248290376e-1 -7.830458246854587e-1 -7.830458245406656e-1 -7.811155902139214e-1 -7.811155901273713e-1
          -4.353031718094805e-1 -4.084017573306121e-1 -4.084017572570509e-1 -4.084017571689307e-1 -2.308618498763471e-1
          -8.889775990980905e-2 -8.889775926351732e-2 -8.889775744800893e-2 -4.944125254800450e-2 -4.944125222531181e-2
          -1.704933612498828e-2 -1.704933610431891e-2 -1.704933573466774e-2 -9.293306554619429e-3 -9.293306151620657e-3
          -9.293302867349801e-3 5.186661020471657e-2 1.520537513409924e-1
          </eigenvalues>
        <occupations size="23">
          1.000000000000000e0 1.000000000000000e0 1.000000000000000e0 1.000000000000000e0 1.000000000000000e0
          1.000000000000000e0 1.000000000000000e0 1.000000000000000e0 1.000000000000000e0 1.000000000000000e0
          1.000000000000000e0 1.000000000000000e0 1.000000000000000e0 1.000000000000000e0 1.000000000000000e0
          1.000000000000000e0 1.000000000000000e0 1.000000000000000e0 1.000000000000000e0 1.000000000000000e0
          1.000000000000000e0 0.000000000000000e0 0.000000000000000e0
          </occupations>
      </ks_energies>
      <ks_energies>
        <k_point weight="7.500000000000e-1">0.000000000000000e0 0.000000000000000e0 -5.000000000000000e-1</k_point>
        <npw>8642</npw>
        <eigenvalues size="23">
          -7.831301223381590e-1 -7.831301222067473e-1 -7.830986090590352e-1 -7.811390913526766e-1 -7.811297115672913e-1
          -4.332723914538978e-1 -4.111606415682867e-1 -4.083416143513831e-1 -4.083416142438534e-1 -2.286641844741076e-1
          -9.456014302997096e-2 -9.004047147720737e-2 -9.004047106492763e-2 -4.090233667223639e-2 -3.431431860216569e-2
          -3.211916808111460e-2 -2.852501497312775e-2 -1.769357192079511e-2 -1.769357093309484e-2 -1.042515283628928e-2
          -1.042515245285169e-2 7.226418191655965e-2 1.466420639825230e-1
          </eigenvalues>
        <occupations size="23">
          1.000000000000000e0 1.000000000000000e0 1.000000000000000e0 1.000000000000000e0 1.000000000000000e0
          1.000000000000000e0 1.000000000000000e0 1.000000000000000e0 1.000000000000000e0 1.000000000000000e0
          1.000000000000000e0 1.000000000000000e0 1.000000000000000e0 1.000000000000000e0 1.000000000000000e0
          1.000000000000000e0 1.000000000000000e0 1.000000000000000e0 1.000000000000000e0 1.000000000000000e0
          1.000000000000000e0 0.000000000000000e0 0.000000000000000e0
          </occupations>
      </ks_energies>
      <ks_energies>
        <k_point weight="7.500000000000e-1">0.000000000000000e0 -5.000000000000000e-1 -5.000000000000000e-1</k_point>
        <npw>8604</npw>
        <eigenvalues size="23">
          -7.831138900306600e-1 -7.831138899197668e-1 -7.830148290468358e-1 -7.810953758551038e-1 -7.810158870706077e-1
          -4.317808200536692e-1 -4.102108758740690e-1 -4.102108752339263e-1 -4.091677619040833e-1 -2.284724622520807e-1
          -9.949967374013978e-2 -9.051128733937691e-2 -9.051128409152197e-2 -3.859401658612653e-2 -3.859401646697498e-2
          -3.326597056011060e-2 -2.498377627491522e-2 -1.494731151817880e-2 -1.494731146035982e-2 -1.382114404572099e-2
          -4.165939268913466e-3 7.159720702172583e-2 1.517236043678816e-1
          </eigenvalues>
        <occupations size="23">
          1.000000000000000e0 1.000000000000000e0 1.000000000000000e0 1.000000000000000e0 1.000000000000000e0
          1.000000000000000e0 1.000000000000000e0 1.000000000000000e0 1.000000000000000e0 1.000000000000000e0
          1.000000000000000e0 1.000000000000000e0 1.000000000000000e0 1.000000000000000e0 1.000000000000000e0
          1.000000000000000e0 1.000000000000000e0 1.000000000000000e0 1.000000000000000e0 1.000000000000000e0
          1.000000000000000e0 0.000000000000000e0 0.000000000000000e0
          </occupations>
      </ks_energies>
      <ks_energies>
        <k_point weight="2.500000000000e-1">-5.000000000000000e-1 -5.000000000000000e-1 -5.000000000000000e-1</k_point>
        <npw>8552</npw>
        <eigenvalues size="23">
          -7.830311755970753e-1 -7.830311755452680e-1 -7.830311754159384e-1 -7.809638300114385e-1 -7.809638299368158e-1
          -4.308509516098217e-1 -4.101267459045808e-1 -4.101267456835419e-1 -4.101267453802792e-1 -2.304327219021356e-1
          -9.649424379327222e-2 -9.649424336388662e-2 -9.649424242369200e-2 -3.595863375169844e-2 -3.595863361950696e-2
          -3.595863286267460e-2 -1.193122493792055e-2 -1.193122302484774e-2 -5.928240005688810e-3 -5.928239866787505e-3
          -5.928239706237218e-3 5.051018232559548e-2 1.623370522048773e-1
          </eigenvalues>
        <occupations size="23">
          1.000000000000000e0 1.000000000000000e0 1.000000000000000e0 1.000000000000000e0 1.000000000000000e0
          1.000000000000000e0 1.000000000000000e0 1.000000000000000e0 1.000000000000000e0 1.000000000000000e0
          1.000000000000000e0 1.000000000000000e0 1.000000000000000e0 1.000000000000000e0 1.000000000000000e0
          1.000000000000000e0 1.000000000000000e0 1.000000000000000e0 1.000000000000000e0 1.000000000000000e0
          1.000000000000000e0 0.000000000000000e0 0.000000000000000e0
          </occupations>
      </ks_energies>
    </band_structure>
    <forces rank="2" dims="3 5" order="F">
      0.000000000000000e0 0.000000000000000e0 0.000000000000000e0
      -3.716119724321543e-4 3.716119724321543e-4 3.716119724321543e-4
      3.716119724321543e-4 -3.716119724321543e-4 3.716119724321543e-4
      3.716119724321543e-4 3.716119724321543e-4 -3.716119724321543e-4
      -3.716119724321543e-4 -3.716119724321543e-4 -3.716119724321543e-4
      </forces>
    <stress rank="2" dims="3 3" order="F">
      -5.054224335381676e-5 0.000000000000000e0 0.000000000000000e0
      0.000000000000000e0 -5.054224335381676e-5 0.000000000000000e0
      0.000000000000000e0 0.000000000000000e0 -5.054224335381676e-5
      </stress>
  </output>
  <status>0</status>
  <timing_info>
    <total label="PWSCF">
      <cpu>2.008677600000000e1</cpu>
      <wall>2.098858189582825e1</wall>
    </total>
    <partial label="electrons" calls="1">
      <cpu>1.460358800000000e1</cpu>
      <wall>1.488807106018067e1</wall>
    </partial>
  </timing_info>
  <closed DATE="15 Jan 2021" TIME="14:18:58"></closed>
</qes:espresso>
