<?xml version="1.0" encoding="UTF-8"?>
<qes:espresso xsi:schemaLocation="http://www.quantum-espresso.org/ns/qes/qes-1.0 http://www.quantum-espresso.org/ns/qes/qes_030920.xsd" Units="Hartree atomic units" xmlns:xsi="http://www.w3.org/2001/XMLSchema-instance" xmlns:qes="http://www.quantum-espresso.org/ns/qes/qes-1.0">
  <!--All quantities are in Hartree atomic units unless otherwise specified-->
  <general_info>
    <xml_format NAME="QEXSD" VERSION="20.04.20">QEXSD_20.04.20</xml_format>
    <creator NAME="PWSCF" VERSION="6.7MaX">XML file generated by PWSCF</creator>
    <created DATE="15Jan2021" TIME="16:51:45">This run was terminated on:  16:51:45  15 Jan 2021</created>
    <job>SnI4un</job>
  </general_info>
  <parallel_info>
    <nprocs>32</nprocs>
    <nthreads>1</nthreads>
    <ntasks>1</ntasks>
    <nbgrp>1</nbgrp>
    <npool>1</npool>
    <ndiag>32</ndiag>
  </parallel_info>
  <input>
    <control_variables>
      <title>SnI4un</title>
      <calculation>vc-relax</calculation>
      <restart_mode>from_scratch</restart_mode>
      <prefix>SnI4un</prefix>
      <pseudo_dir>../../pseudo/</pseudo_dir>
      <outdir>./out</outdir>
      <stress>true</stress>
      <forces>true</forces>
      <wf_collect>true</wf_collect>
      <disk_io>low</disk_io>
      <max_seconds>42500</max_seconds>
      <nstep>50</nstep>
      <etot_conv_thr>5.000000000000000e-5</etot_conv_thr>
      <forc_conv_thr>5.000000000000000e-5</forc_conv_thr>
      <press_conv_thr>5.000000000000000e-1</press_conv_thr>
      <verbosity>medium</verbosity>
      <print_every>100000</print_every>
    </control_variables>
    <atomic_species ntyp="2">
      <species name="Sn">
        <mass>1.187000000000000e2</mass>
        <pseudo_file>Sn.pbe-dn-kjpaw_psl.1.0.0.UPF</pseudo_file>
      </species>
      <species name="I">
        <mass>1.269000000000000e2</mass>
        <pseudo_file>I.pbe-n-kjpaw_psl.1.0.0.UPF</pseudo_file>
      </species>
    </atomic_species>
    <atomic_structure nat="5" alat="1.263551767203e1">
      <atomic_positions>
        <atom name="Sn" index="1">0.000000000000000e0 0.000000000000000e0 0.000000000000000e0</atom>
        <atom name="I" index="2">2.955485490040655e0 9.680032181988585e0 9.680032181988585e0</atom>
        <atom name="I" index="3">9.680032181988585e0 2.955485490040655e0 9.680032181988585e0</atom>
        <atom name="I" index="4">9.680032181988585e0 9.680032181988585e0 2.955485490040655e0</atom>
        <atom name="I" index="5">2.955485490040655e0 2.955485490040655e0 2.955485490040655e0</atom>
      </atomic_positions>
      <cell>
        <a1>1.263551767202924e1 0.000000000000000e0 0.000000000000000e0</a1>
        <a2>0.000000000000000e0 1.263551767202924e1 0.000000000000000e0</a2>
        <a3>0.000000000000000e0 0.000000000000000e0 1.263551767202924e1</a3>
      </cell>
    </atomic_structure>
    <dft>
      <functional>PBE</functional>
    </dft>
    <spin>
      <lsda>false</lsda>
      <noncolin>false</noncolin>
      <spinorbit>false</spinorbit>
    </spin>
    <bands>
      <nbnd>23</nbnd>
      <tot_charge>0.000000000000000e0</tot_charge>
      <occupations>fixed</occupations>
    </bands>
    <basis>
      <gamma_only>false</gamma_only>
      <ecutwfc>3.500000000000000e1</ecutwfc>
      <ecutrho>1.400000000000000e2</ecutrho>
    </basis>
    <electron_control>
      <diagonalization>davidson</diagonalization>
      <mixing_mode>plain</mixing_mode>
      <mixing_beta>5.000000000000000e-1</mixing_beta>
      <conv_thr>5.000000000000000e-7</conv_thr>
      <mixing_ndim>8</mixing_ndim>
      <max_nstep>100</max_nstep>
      <real_space_q>false</real_space_q>
      <real_space_beta>false</real_space_beta>
      <tq_smoothing>false</tq_smoothing>
      <tbeta_smoothing>false</tbeta_smoothing>
      <diago_thr_init>0.000000000000000e0</diago_thr_init>
      <diago_full_acc>false</diago_full_acc>
      <diago_cg_maxiter>20</diago_cg_maxiter>
      <diago_ppcg_maxiter>20</diago_ppcg_maxiter>
    </electron_control>
    <k_points_IBZ>
      <monkhorst_pack nk1="4" nk2="4" nk3="4" k1="0" k2="0" k3="0">Monkhorst-Pack</monkhorst_pack>
    </k_points_IBZ>
    <ion_control>
      <ion_dynamics>bfgs</ion_dynamics>
      <upscale>1.000000000000000e2</upscale>
      <remove_rigid_rot>false</remove_rigid_rot>
      <refold_pos>false</refold_pos>
      <bfgs>
        <ndim>1</ndim>
        <trust_radius_min>1.000000000000000e-4</trust_radius_min>
        <trust_radius_max>8.000000000000000e-1</trust_radius_max>
        <trust_radius_init>5.000000000000000e-1</trust_radius_init>
        <w1>1.000000000000000e-2</w1>
        <w2>5.000000000000000e-1</w2>
      </bfgs>
    </ion_control>
    <cell_control>
      <cell_dynamics>bfgs</cell_dynamics>
      <pressure>0.000000000000000e0</pressure>
      <wmass>6.263000000000000e2</wmass>
      <cell_factor>0.000000000000000e0</cell_factor>
      <fix_volume>false</fix_volume>
      <fix_area>false</fix_area>
      <isotropic>false</isotropic>
    </cell_control>
    <symmetry_flags>
      <nosym>false</nosym>
      <nosym_evc>false</nosym_evc>
      <noinv>false</noinv>
      <no_t_rev>false</no_t_rev>
      <force_symmorphic>false</force_symmorphic>
      <use_all_frac>false</use_all_frac>
    </symmetry_flags>
    <free_positions rank="2" dims="3 5" order="F">
      1 1 1
      1 1 1
      1 1 1
      1 1 1
      1 1 1
      </free_positions>
  </input>
  <step n_step="1">
    <scf_conv>
      <convergence_achieved>true</convergence_achieved>
      <n_scf_steps>7</n_scf_steps>
      <scf_error>9.460760517746220e-7</scf_error>
    </scf_conv>
    <atomic_structure nat="5" alat="1.263551767203e1">
      <atomic_positions>
        <atom name="Sn" index="1">0.000000000000000e0 0.000000000000000e0 0.000000000000000e0</atom>
        <atom name="I" index="2">2.955485490040655e0 9.680032181988585e0 9.680032181988585e0</atom>
        <atom name="I" index="3">9.680032181988585e0 2.955485490040655e0 9.680032181988585e0</atom>
        <atom name="I" index="4">9.680032181988585e0 9.680032181988585e0 2.955485490040655e0</atom>
        <atom name="I" index="5">2.955485490040655e0 2.955485490040655e0 2.955485490040655e0</atom>
      </atomic_positions>
      <cell>
        <a1>1.263551767202924e1 0.000000000000000e0 0.000000000000000e0</a1>
        <a2>0.000000000000000e0 1.263551767202924e1 0.000000000000000e0</a2>
        <a3>0.000000000000000e0 0.000000000000000e0 1.263551767202924e1</a3>
      </cell>
    </atomic_structure>
    <total_energy>
      <etot>-9.789203899584255e2</etot>
      <eband>-1.252963287684157e1</eband>
      <ehart>4.735873926551895e1</ehart>
      <vtxc>-2.680220111410925e1</vtxc>
      <etxc>-5.549399344994203e1</etxc>
      <ewald>-5.971649898123508e1</ewald>
    </total_energy>
    <forces rank="2" dims="3 5" order="F">
      0.000000000000000e0 0.000000000000000e0 0.000000000000000e0
      -1.912629753709709e-4 1.912629753709709e-4 1.912629753709709e-4
      1.912629753709709e-4 -1.912629753709709e-4 1.912629753709709e-4
      1.912629753709709e-4 1.912629753709709e-4 -1.912629753709709e-4
      -1.912629753709709e-4 -1.912629753709709e-4 -1.912629753709709e-4
      </forces>
  </step>
  <step n_step="2">
    <scf_conv>
      <convergence_achieved>true</convergence_achieved>
      <n_scf_steps>4</n_scf_steps>
      <scf_error>3.552329155676166e-7</scf_error>
    </scf_conv>
    <atomic_structure nat="5" alat="1.263551767203e1">
      <atomic_positions>
        <atom name="Sn" index="1">0.000000000000000e0 0.000000000000000e0 0.000000000000000e0</atom>
        <atom name="I" index="2">2.954957387583349e0 9.679937824063403e0 9.679937824063403e0</atom>
        <atom name="I" index="3">9.679937824063403e0 2.954957387583349e0 9.679937824063403e0</atom>
        <atom name="I" index="4">9.679937824063403e0 9.679937824063403e0 2.954957387583349e0</atom>
        <atom name="I" index="5">2.954957387583349e0 2.954957387583349e0 2.954957387583349e0</atom>
      </atomic_positions>
      <cell>
        <a1>1.263489521164675e1 0.000000000000000e0 0.000000000000000e0</a1>
        <a2>0.000000000000000e0 1.263489521164675e1 0.000000000000000e0</a2>
        <a3>0.000000000000000e0 0.000000000000000e0 1.263489521164675e1</a3>
      </cell>
    </atomic_structure>
    <total_energy>
      <etot>-9.789203903446037e2</etot>
      <eband>-1.252926255776652e1</eband>
      <ehart>4.736692792943288e1</ehart>
      <vtxc>-2.680266660054411e1</vtxc>
      <etxc>-5.549434802813159e1</etxc>
      <ewald>-5.971073030822225e1</ewald>
    </total_energy>
    <forces rank="2" dims="3 5" order="F">
      0.000000000000000e0 0.000000000000000e0 0.000000000000000e0
      -1.083625108787096e-4 1.083625108787096e-4 1.083625108787096e-4
      1.083625108787096e-4 -1.083625108787096e-4 1.083625108787096e-4
      1.083625108787096e-4 1.083625108787096e-4 -1.083625108787096e-4
      -1.083625108787096e-4 -1.083625108787096e-4 -1.083625108787096e-4
      </forces>
  </step>
  <step n_step="3">
    <scf_conv>
      <convergence_achieved>true</convergence_achieved>
      <n_scf_steps>8</n_scf_steps>
      <scf_error>6.230306620018588e-9</scf_error>
    </scf_conv>
    <atomic_structure nat="5" alat="1.263551767203e1">
      <atomic_positions>
        <atom name="Sn" index="1">0.000000000000000e0 0.000000000000000e0 0.000000000000000e0</atom>
        <atom name="I" index="2">2.954500542434704e0 9.680365633470103e0 9.680365633470103e0</atom>
        <atom name="I" index="3">9.680365633470103e0 2.954500542434704e0 9.680365633470103e0</atom>
        <atom name="I" index="4">9.680365633470103e0 9.680365633470103e0 2.954500542434704e0</atom>
        <atom name="I" index="5">2.954500542434704e0 2.954500542434704e0 2.954500542434704e0</atom>
      </atomic_positions>
      <cell>
        <a1>1.263486617590481e1 0.000000000000000e0 0.000000000000000e0</a1>
        <a2>0.000000000000000e0 1.263486617590481e1 0.000000000000000e0</a2>
        <a3>0.000000000000000e0 0.000000000000000e0 1.263486617590481e1</a3>
      </cell>
    </atomic_structure>
    <total_energy>
      <etot>-9.789203912304318e2</etot>
      <eband>-1.253138201962184e1</eband>
      <ehart>4.738029043597272e1</ehart>
      <vtxc>-2.680337401129253e1</vtxc>
      <etxc>-5.549493049316753e1</etxc>
      <ewald>-5.970061329435294e1</ewald>
    </total_energy>
    <forces rank="2" dims="3 5" order="F">
      0.000000000000000e0 0.000000000000000e0 0.000000000000000e0
      -1.250361169168940e-4 1.250361169168940e-4 1.250361169168940e-4
      1.250361169168940e-4 -1.250361169168940e-4 1.250361169168940e-4
      1.250361169168940e-4 1.250361169168940e-4 -1.250361169168940e-4
      -1.250361169168940e-4 -1.250361169168940e-4 -1.250361169168940e-4
      </forces>
  </step>
  <step n_step="4">
    <scf_conv>
      <convergence_achieved>true</convergence_achieved>
      <n_scf_steps>7</n_scf_steps>
      <scf_error>4.010514148330624e-10</scf_error>
    </scf_conv>
    <atomic_structure nat="5" alat="1.263551767203e1">
      <atomic_positions>
        <atom name="Sn" index="1">0.000000000000000e0 0.000000000000000e0 0.000000000000000e0</atom>
        <atom name="I" index="2">2.953981752216849e0 9.680782924543433e0 9.680782924543433e0</atom>
        <atom name="I" index="3">9.680782924543433e0 2.953981752216849e0 9.680782924543433e0</atom>
        <atom name="I" index="4">9.680782924543433e0 9.680782924543433e0 2.953981752216849e0</atom>
        <atom name="I" index="5">2.953981752216849e0 2.953981752216849e0 2.953981752216849e0</atom>
      </atomic_positions>
      <cell>
        <a1>1.263476467676028e1 0.000000000000000e0 0.000000000000000e0</a1>
        <a2>0.000000000000000e0 1.263476467676028e1 0.000000000000000e0</a2>
        <a3>0.000000000000000e0 0.000000000000000e0 1.263476467676028e1</a3>
      </cell>
    </atomic_structure>
    <total_energy>
      <etot>-9.789203916900249e2</etot>
      <eband>-1.253151432374938e1</eband>
      <ehart>4.739083404462465e1</ehart>
      <vtxc>-2.680385782983171e1</vtxc>
      <etxc>-5.549531149494912e1</etxc>
      <ewald>-5.968980645763651e1</ewald>
    </total_energy>
    <forces rank="2" dims="3 5" order="F">
      0.000000000000000e0 0.000000000000000e0 0.000000000000000e0
      -7.135895864247637e-5 7.135895864247638e-5 7.135895864247638e-5
      7.135895864247638e-5 -7.135895864247638e-5 7.135895864247638e-5
      7.135895864247638e-5 7.135895864247637e-5 -7.135895864247637e-5
      -7.135895864247637e-5 -7.135895864247637e-5 -7.135895864247637e-5
      </forces>
  </step>
  <step n_step="5">
    <scf_conv>
      <convergence_achieved>true</convergence_achieved>
      <n_scf_steps>7</n_scf_steps>
      <scf_error>6.043227101411437e-10</scf_error>
    </scf_conv>
    <atomic_structure nat="5" alat="1.263551767203e1">
      <atomic_positions>
        <atom name="Sn" index="1">0.000000000000000e0 0.000000000000000e0 0.000000000000000e0</atom>
        <atom name="I" index="2">2.953526203946146e0 9.681141292059825e0 9.681141292059825e0</atom>
        <atom name="I" index="3">9.681141292059825e0 2.953526203946146e0 9.681141292059825e0</atom>
        <atom name="I" index="4">9.681141292059825e0 9.681141292059825e0 2.953526203946146e0</atom>
        <atom name="I" index="5">2.953526203946146e0 2.953526203946146e0 2.953526203946146e0</atom>
      </atomic_positions>
      <cell>
        <a1>1.263466749600597e1 0.000000000000000e0 0.000000000000000e0</a1>
        <a2>0.000000000000000e0 1.263466749600597e1 0.000000000000000e0</a2>
        <a3>0.000000000000000e0 0.000000000000000e0 1.263466749600597e1</a3>
      </cell>
    </atomic_structure>
    <total_energy>
      <etot>-9.789203918299426e2</etot>
      <eband>-1.253162868278233e1</eband>
      <ehart>4.740024268770297e1</ehart>
      <vtxc>-2.680427698163315e1</vtxc>
      <etxc>-5.549563925730834e1</etxc>
      <ewald>-5.968039194497826e1</ewald>
    </total_energy>
    <forces rank="2" dims="3 5" order="F">
      0.000000000000000e0 0.000000000000000e0 0.000000000000000e0
      -2.874895380737875e-5 2.874895380737875e-5 2.874895380737875e-5
      2.874895380737875e-5 -2.874895380737875e-5 2.874895380737875e-5
      2.874895380737875e-5 2.874895380737875e-5 -2.874895380737875e-5
      -2.874895380737875e-5 -2.874895380737875e-5 -2.874895380737875e-5
      </forces>
  </step>
  <step n_step="6">
    <scf_conv>
      <convergence_achieved>true</convergence_achieved>
      <n_scf_steps>12</n_scf_steps>
      <scf_error>4.433924184003450e-10</scf_error>
    </scf_conv>
    <atomic_structure nat="5" alat="1.263551767203e1">
      <atomic_positions>
        <atom name="Sn" index="1">0.000000000000000e0 0.000000000000000e0 0.000000000000000e0</atom>
        <atom name="I" index="2">2.953919723222759e0 9.682677182817606e0 9.682677182817606e0</atom>
        <atom name="I" index="3">9.682677182817606e0 2.953919723222759e0 9.682677182817606e0</atom>
        <atom name="I" index="4">9.682677182817606e0 9.682677182817606e0 2.953919723222759e0</atom>
        <atom name="I" index="5">2.953919723222759e0 2.953919723222759e0 2.953919723222759e0</atom>
      </atomic_positions>
      <cell>
        <a1>1.263659690604036e1 0.000000000000000e0 0.000000000000000e0</a1>
        <a2>0.000000000000000e0 1.263659690604036e1 0.000000000000000e0</a2>
        <a3>0.000000000000000e0 0.000000000000000e0 1.263659690604036e1</a3>
      </cell>
    </atomic_structure>
    <total_energy>
      <etot>-9.789203945261221e2</etot>
      <eband>-1.253582673683695e1</eband>
      <ehart>4.740641998946505e1</ehart>
      <vtxc>-2.680388286369531e1</vtxc>
      <etxc>-5.549533697731635e1</etxc>
      <ewald>-5.966996784620744e1</ewald>
    </total_energy>
    <forces rank="2" dims="3 5" order="F">
      0.000000000000000e0 0.000000000000000e0 0.000000000000000e0
      -6.973432286388608e-5 6.973432286388608e-5 6.973432286388608e-5
      6.973432286388608e-5 -6.973432286388608e-5 6.973432286388608e-5
      6.973432286388608e-5 6.973432286388608e-5 -6.973432286388608e-5
      -6.973432286388608e-5 -6.973432286388604e-5 -6.973432286388608e-5
      </forces>
  </step>
  <step n_step="7">
    <scf_conv>
      <convergence_achieved>true</convergence_achieved>
      <n_scf_steps>11</n_scf_steps>
      <scf_error>3.439498079595235e-9</scf_error>
    </scf_conv>
    <atomic_structure nat="5" alat="1.263551767203e1">
      <atomic_positions>
        <atom name="Sn" index="1">0.000000000000000e0 0.000000000000000e0 0.000000000000000e0</atom>
        <atom name="I" index="2">2.954297783426780e0 9.684421473651421e0 9.684421473651421e0</atom>
        <atom name="I" index="3">9.684421473651421e0 2.954297783426780e0 9.684421473651421e0</atom>
        <atom name="I" index="4">9.684421473651421e0 9.684421473651421e0 2.954297783426780e0</atom>
        <atom name="I" index="5">2.954297783426780e0 2.954297783426780e0 2.954297783426780e0</atom>
      </atomic_positions>
      <cell>
        <a1>1.263871925707820e1 0.000000000000000e0 0.000000000000000e0</a1>
        <a2>0.000000000000000e0 1.263871925707820e1 0.000000000000000e0</a2>
        <a3>0.000000000000000e0 0.000000000000000e0 1.263871925707820e1</a3>
      </cell>
    </atomic_structure>
    <total_energy>
      <etot>-9.789203973320312e2</etot>
      <eband>-1.254053924823012e1</eband>
      <ehart>4.741461565438118e1</ehart>
      <vtxc>-2.680350008837940e1</vtxc>
      <etxc>-5.549504280572825e1</etxc>
      <ewald>-5.965725525423733e1</ewald>
    </total_energy>
    <forces rank="2" dims="3 5" order="F">
      0.000000000000000e0 0.000000000000000e0 0.000000000000000e0
      -1.099891434204211e-4 1.099891434204211e-4 1.099891434204211e-4
      1.099891434204211e-4 -1.099891434204211e-4 1.099891434204211e-4
      1.099891434204211e-4 1.099891434204211e-4 -1.099891434204211e-4
      -1.099891434204211e-4 -1.099891434204211e-4 -1.099891434204211e-4
      </forces>
  </step>
  <step n_step="8">
    <scf_conv>
      <convergence_achieved>true</convergence_achieved>
      <n_scf_steps>15</n_scf_steps>
      <scf_error>2.283183416364500e-9</scf_error>
    </scf_conv>
    <atomic_structure nat="5" alat="1.263551767203e1">
      <atomic_positions>
        <atom name="Sn" index="1">0.000000000000000e0 0.000000000000000e0 0.000000000000000e0</atom>
        <atom name="I" index="2">2.954792260204257e0 9.687110523430698e0 9.687110523430698e0</atom>
        <atom name="I" index="3">9.687110523430698e0 2.954792260204257e0 9.687110523430698e0</atom>
        <atom name="I" index="4">9.687110523430698e0 9.687110523430698e0 2.954792260204257e0</atom>
        <atom name="I" index="5">2.954792260204257e0 2.954792260204257e0 2.954792260204257e0</atom>
      </atomic_positions>
      <cell>
        <a1>1.264190278363495e1 0.000000000000000e0 0.000000000000000e0</a1>
        <a2>0.000000000000000e0 1.264190278363495e1 0.000000000000000e0</a2>
        <a3>0.000000000000000e0 0.000000000000000e0 1.264190278363495e1</a3>
      </cell>
    </atomic_structure>
    <total_energy>
      <etot>-9.789204013253721e2</etot>
      <eband>-1.254743031048553e1</eband>
      <ehart>4.742797171751112e1</ehart>
      <vtxc>-2.680292361850979e1</vtxc>
      <etxc>-5.549459165397006e1</etxc>
      <ewald>-5.963653950574815e1</ewald>
    </total_energy>
    <forces rank="2" dims="3 5" order="F">
      0.000000000000000e0 0.000000000000000e0 0.000000000000000e0
      -1.522445063330618e-4 1.522445063330618e-4 1.522445063330618e-4
      1.522445063330618e-4 -1.522445063330618e-4 1.522445063330618e-4
      1.522445063330618e-4 1.522445063330618e-4 -1.522445063330618e-4
      -1.522445063330618e-4 -1.522445063330618e-4 -1.522445063330618e-4
      </forces>
  </step>
  <step n_step="9">
    <scf_conv>
      <convergence_achieved>true</convergence_achieved>
      <n_scf_steps>13</n_scf_steps>
      <scf_error>9.808058830022542e-9</scf_error>
    </scf_conv>
    <atomic_structure nat="5" alat="1.263551767203e1">
      <atomic_positions>
        <atom name="Sn" index="1">0.000000000000000e0 0.000000000000000e0 0.000000000000000e0</atom>
        <atom name="I" index="2">2.955423045787935e0 9.691255027682146e0 9.691255027682146e0</atom>
        <atom name="I" index="3">9.691255027682146e0 2.955423045787935e0 9.691255027682146e0</atom>
        <atom name="I" index="4">9.691255027682146e0 9.691255027682146e0 2.955423045787935e0</atom>
        <atom name="I" index="5">2.955423045787935e0 2.955423045787935e0 2.955423045787935e0</atom>
      </atomic_positions>
      <cell>
        <a1>1.264667807347007e1 0.000000000000000e0 0.000000000000000e0</a1>
        <a2>0.000000000000000e0 1.264667807347007e1 0.000000000000000e0</a2>
        <a3>0.000000000000000e0 0.000000000000000e0 1.264667807347007e1</a3>
      </cell>
    </atomic_structure>
    <total_energy>
      <etot>-9.789204069655288e2</etot>
      <eband>-1.255781417520889e1</eband>
      <ehart>4.745019735966944e1</ehart>
      <vtxc>-2.680223695612820e1</vtxc>
      <etxc>-5.549406983750659e1</etxc>
      <ewald>-5.960295837486616e1</ewald>
    </total_energy>
    <forces rank="2" dims="3 5" order="F">
      0.000000000000000e0 0.000000000000000e0 0.000000000000000e0
      -2.008856028127140e-4 2.008856028127140e-4 2.008856028127140e-4
      2.008856028127140e-4 -2.008856028127140e-4 2.008856028127141e-4
      2.008856028127140e-4 2.008856028127140e-4 -2.008856028127140e-4
      -2.008856028127140e-4 -2.008856028127140e-4 -2.008856028127140e-4
      </forces>
  </step>
  <step n_step="10">
    <scf_conv>
      <convergence_achieved>true</convergence_achieved>
      <n_scf_steps>17</n_scf_steps>
      <scf_error>2.305497729238921e-9</scf_error>
    </scf_conv>
    <atomic_structure nat="5" alat="1.263551767203e1">
      <atomic_positions>
        <atom name="Sn" index="1">0.000000000000000e0 0.000000000000000e0 0.000000000000000e0</atom>
        <atom name="I" index="2">2.956207886306595e0 9.697633121916176e0 9.697633121916176e0</atom>
        <atom name="I" index="3">9.697633121916180e0 2.956207886306595e0 9.697633121916176e0</atom>
        <atom name="I" index="4">9.697633121916180e0 9.697633121916176e0 2.956207886306595e0</atom>
        <atom name="I" index="5">2.956207886306595e0 2.956207886306595e0 2.956207886306595e0</atom>
      </atomic_positions>
      <cell>
        <a1>1.265384100822276e1 0.000000000000000e0 0.000000000000000e0</a1>
        <a2>0.000000000000000e0 1.265384100822276e1 0.000000000000000e0</a2>
        <a3>0.000000000000000e0 0.000000000000000e0 1.265384100822276e1</a3>
      </cell>
    </atomic_structure>
    <total_energy>
      <etot>-9.789204148974996e2</etot>
      <eband>-1.257388461116540e1</eband>
      <ehart>4.748821796943130e1</ehart>
      <vtxc>-2.680134976081249e1</vtxc>
      <etxc>-5.549339045965006e1</etxc>
      <ewald>-5.954895909429917e1</ewald>
    </total_energy>
    <forces rank="2" dims="3 5" order="F">
      0.000000000000000e0 0.000000000000000e0 0.000000000000000e0
      -2.785718261327279e-4 2.785718261327279e-4 2.785718261327279e-4
      2.785718261327279e-4 -2.785718261327279e-4 2.785718261327279e-4
      2.785718261327279e-4 2.785718261327279e-4 -2.785718261327279e-4
      -2.785718261327279e-4 -2.785718261327279e-4 -2.785718261327279e-4
      </forces>
  </step>
  <step n_step="11">
    <scf_conv>
      <convergence_achieved>true</convergence_achieved>
      <n_scf_steps>14</n_scf_steps>
      <scf_error>1.907120118830414e-9</scf_error>
    </scf_conv>
    <atomic_structure nat="5" alat="1.263551767203e1">
      <atomic_positions>
        <atom name="Sn" index="1">0.000000000000000e0 0.000000000000000e0 0.000000000000000e0</atom>
        <atom name="I" index="2">2.957239303130713e0 9.707346107221092e0 9.707346107221092e0</atom>
        <atom name="I" index="3">9.707346107221104e0 2.957239303130712e0 9.707346107221092e0</atom>
        <atom name="I" index="4">9.707346107221104e0 9.707346107221092e0 2.957239303130712e0</atom>
        <atom name="I" index="5">2.957239303130713e0 2.957239303130712e0 2.957239303130712e0</atom>
      </atomic_positions>
      <cell>
        <a1>1.266458541035180e1 0.000000000000000e0 0.000000000000000e0</a1>
        <a2>0.000000000000000e0 1.266458541035179e1 0.000000000000000e0</a2>
        <a3>0.000000000000000e0 0.000000000000000e0 1.266458541035179e1</a3>
      </cell>
    </atomic_structure>
    <total_energy>
      <etot>-9.789204255926961e2</etot>
      <eband>-1.259803030491032e1</eband>
      <ehart>4.754836581599452e1</ehart>
      <vtxc>-2.680018095697440e1</vtxc>
      <etxc>-5.549250395500422e1</etxc>
      <ewald>-5.946475003974621e1</ewald>
    </total_energy>
    <forces rank="2" dims="3 5" order="F">
      0.000000000000000e0 0.000000000000000e0 0.000000000000000e0
      -3.770179215123118e-4 3.770179215123121e-4 3.770179215123120e-4
      3.770179215123118e-4 -3.770179215123121e-4 3.770179215123121e-4
      3.770179215123118e-4 3.770179215123121e-4 -3.770179215123120e-4
      -3.770179215123118e-4 -3.770179215123122e-4 -3.770179215123120e-4
      </forces>
  </step>
  <step n_step="12">
    <scf_conv>
      <convergence_achieved>true</convergence_achieved>
      <n_scf_steps>13</n_scf_steps>
      <scf_error>9.388910544896005e-9</scf_error>
    </scf_conv>
    <atomic_structure nat="5" alat="1.263551767203e1">
      <atomic_positions>
        <atom name="Sn" index="1">0.000000000000000e0 0.000000000000000e0 0.000000000000000e0</atom>
        <atom name="I" index="2">2.958643172227603e0 9.722058841317748e0 9.722058841317748e0</atom>
        <atom name="I" index="3">9.722058841317773e0 2.958643172227601e0 9.722058841317748e0</atom>
        <atom name="I" index="4">9.722058841317773e0 9.722058841317748e0 2.958643172227601e0</atom>
        <atom name="I" index="5">2.958643172227603e0 2.958643172227601e0 2.958643172227601e0</atom>
      </atomic_positions>
      <cell>
        <a1>1.268070201354536e1 0.000000000000000e0 0.000000000000000e0</a1>
        <a2>0.000000000000000e0 1.268070201354533e1 0.000000000000000e0</a2>
        <a3>0.000000000000000e0 0.000000000000000e0 1.268070201354533e1</a3>
      </cell>
    </atomic_structure>
    <total_energy>
      <etot>-9.789204390013424e2</etot>
      <eband>-1.263413903286829e1</eband>
      <ehart>4.764162008065124e1</ehart>
      <vtxc>-2.679855627417712e1</vtxc>
      <etxc>-5.549127206028918e1</etxc>
      <ewald>-5.933542696822761e1</ewald>
    </total_energy>
    <forces rank="2" dims="3 5" order="F">
      0.000000000000000e0 0.000000000000000e0 0.000000000000000e0
      -5.126867023949356e-4 5.126867023949364e-4 5.126867023949364e-4
      5.126867023949356e-4 -5.126867023949364e-4 5.126867023949364e-4
      5.126867023949356e-4 5.126867023949364e-4 -5.126867023949364e-4
      -5.126867023949356e-4 -5.126867023949364e-4 -5.126867023949364e-4
      </forces>
  </step>
  <step n_step="13">
    <scf_conv>
      <convergence_achieved>true</convergence_achieved>
      <n_scf_steps>16</n_scf_steps>
      <scf_error>4.393138064101921e-9</scf_error>
    </scf_conv>
    <atomic_structure nat="5" alat="1.263551767203e1">
      <atomic_positions>
        <atom name="Sn" index="1">0.000000000000000e0 0.000000000000000e0 0.000000000000000e0</atom>
        <atom name="I" index="2">2.960512608932380e0 9.744364309403297e0 9.744364309403297e0</atom>
        <atom name="I" index="3">9.744364309403343e0 2.960512608932376e0 9.744364309403297e0</atom>
        <atom name="I" index="4">9.744364309403343e0 9.744364309403297e0 2.960512608932376e0</atom>
        <atom name="I" index="5">2.960512608932380e0 2.960512608932376e0 2.960512608932376e0</atom>
      </atomic_positions>
      <cell>
        <a1>1.270487691833569e1 0.000000000000000e0 0.000000000000000e0</a1>
        <a2>0.000000000000000e0 1.270487691833565e1 0.000000000000000e0</a2>
        <a3>0.000000000000000e0 0.000000000000000e0 1.270487691833565e1</a3>
      </cell>
    </atomic_structure>
    <total_energy>
      <etot>-9.789204541154486e2</etot>
      <eband>-1.268783928729897e1</eband>
      <ehart>4.778578709861340e1</ehart>
      <vtxc>-2.679623542117215e1</vtxc>
      <etxc>-5.548949687969865e1</etxc>
      <ewald>-5.913662203217172e1</ewald>
    </total_energy>
    <forces rank="2" dims="3 5" order="F">
      0.000000000000000e0 0.000000000000000e0 0.000000000000000e0
      -6.782099066399626e-4 6.782099066399648e-4 6.782099066399648e-4
      6.782099066399626e-4 -6.782099066399651e-4 6.782099066399648e-4
      6.782099066399626e-4 6.782099066399651e-4 -6.782099066399648e-4
      -6.782099066399628e-4 -6.782099066399648e-4 -6.782099066399651e-4
      </forces>
  </step>
  <step n_step="14">
    <scf_conv>
      <convergence_achieved>true</convergence_achieved>
      <n_scf_steps>16</n_scf_steps>
      <scf_error>1.383655142902721e-9</scf_error>
    </scf_conv>
    <atomic_structure nat="5" alat="1.263551767203e1">
      <atomic_positions>
        <atom name="Sn" index="1">0.000000000000000e0 0.000000000000000e0 0.000000000000000e0</atom>
        <atom name="I" index="2">2.962505449900350e0 9.777411750331517e0 9.777411750331517e0</atom>
        <atom name="I" index="3">9.777411750331595e0 2.962505449900343e0 9.777411750331517e0</atom>
        <atom name="I" index="4">9.777411750331595e0 9.777411750331517e0 2.962505449900343e0</atom>
        <atom name="I" index="5">2.962505449900350e0 2.962505449900343e0 2.962505449900343e0</atom>
      </atomic_positions>
      <cell>
        <a1>1.273991720023190e1 0.000000000000000e0 0.000000000000000e0</a1>
        <a2>0.000000000000000e0 1.273991720023182e1 0.000000000000000e0</a2>
        <a3>0.000000000000000e0 0.000000000000000e0 1.273991720023182e1</a3>
      </cell>
    </atomic_structure>
    <total_energy>
      <etot>-9.789204709088541e2</etot>
      <eband>-1.276558599001348e1</eband>
      <ehart>4.801051007745897e1</ehart>
      <vtxc>-2.679364369118360e1</vtxc>
      <etxc>-5.548754284531762e1</etxc>
      <ewald>-5.883327830465902e1</ewald>
    </total_energy>
    <forces rank="2" dims="3 5" order="F">
      0.000000000000000e0 0.000000000000000e0 0.000000000000000e0
      -8.590028841065521e-4 8.590028841065573e-4 8.590028841065573e-4
      8.590028841065521e-4 -8.590028841065571e-4 8.590028841065571e-4
      8.590028841065521e-4 8.590028841065573e-4 -8.590028841065571e-4
      -8.590028841065521e-4 -8.590028841065571e-4 -8.590028841065571e-4
      </forces>
  </step>
  <step n_step="15">
    <scf_conv>
      <convergence_achieved>true</convergence_achieved>
      <n_scf_steps>18</n_scf_steps>
      <scf_error>8.668863918253905e-10</scf_error>
    </scf_conv>
    <atomic_structure nat="5" alat="1.263551767203e1">
      <atomic_positions>
        <atom name="Sn" index="1">0.000000000000000e0 0.000000000000000e0 0.000000000000000e0</atom>
        <atom name="I" index="2">2.963836482968954e0 9.814625027348720e0 9.814625027348720e0</atom>
        <atom name="I" index="3">9.814625027348837e0 2.963836482968944e0 9.814625027348720e0</atom>
        <atom name="I" index="4">9.814625027348837e0 9.814625027348720e0 2.963836482968944e0</atom>
        <atom name="I" index="5">2.963836482968954e0 2.963836482968944e0 2.963836482968944e0</atom>
      </atomic_positions>
      <cell>
        <a1>1.277846151031773e1 0.000000000000000e0 0.000000000000000e0</a1>
        <a2>0.000000000000000e0 1.277846151031762e1 0.000000000000000e0</a2>
        <a3>0.000000000000000e0 0.000000000000000e0 1.277846151031762e1</a3>
      </cell>
    </atomic_structure>
    <total_energy>
      <etot>-9.789204869717260e2</etot>
      <eband>-1.285070531015866e1</eband>
      <ehart>4.827626470302910e1</ehart>
      <vtxc>-2.679160123589789e1</vtxc>
      <etxc>-5.548602192810859e1</etxc>
      <ewald>-5.848142347128183e1</ewald>
    </total_energy>
    <forces rank="2" dims="3 5" order="F">
      0.000000000000000e0 0.000000000000000e0 0.000000000000000e0
      -9.790123351392316e-4 9.790123351392401e-4 9.790123351392401e-4
      9.790123351392312e-4 -9.790123351392401e-4 9.790123351392399e-4
      9.790123351392312e-4 9.790123351392401e-4 -9.790123351392401e-4
      -9.790123351392316e-4 -9.790123351392401e-4 -9.790123351392401e-4
      </forces>
  </step>
  <step n_step="16">
    <scf_conv>
      <convergence_achieved>true</convergence_achieved>
      <n_scf_steps>16</n_scf_steps>
      <scf_error>6.777704076969451e-9</scf_error>
    </scf_conv>
    <atomic_structure nat="5" alat="1.263551767203e1">
      <atomic_positions>
        <atom name="Sn" index="1">0.000000000000000e0 0.000000000000000e0 0.000000000000000e0</atom>
        <atom name="I" index="2">2.963688196062480e0 9.850852442264317e0 9.850852442264317e0</atom>
        <atom name="I" index="3">9.850852442264472e0 2.963688196062467e0 9.850852442264317e0</atom>
        <atom name="I" index="4">9.850852442264472e0 9.850852442264317e0 2.963688196062467e0</atom>
        <atom name="I" index="5">2.963688196062480e0 2.963688196062467e0 2.963688196062467e0</atom>
      </atomic_positions>
      <cell>
        <a1>1.281454063832688e1 0.000000000000000e0 0.000000000000000e0</a1>
        <a2>0.000000000000000e0 1.281454063832673e1 0.000000000000000e0</a2>
        <a3>0.000000000000000e0 0.000000000000000e0 1.281454063832673e1</a3>
      </cell>
    </atomic_structure>
    <total_energy>
      <etot>-9.789205101867276e2</etot>
      <eband>-1.293081706588057e1</eband>
      <ehart>4.855667047943379e1</ehart>
      <vtxc>-2.679099192991185e1</vtxc>
      <etxc>-5.548561182167891e1</etxc>
      <ewald>-5.812133582233111e1</ewald>
    </total_energy>
    <forces rank="2" dims="3 5" order="F">
      0.000000000000000e0 0.000000000000000e0 0.000000000000000e0
      -9.699663888937602e-4 9.699663888937716e-4 9.699663888937717e-4
      9.699663888937602e-4 -9.699663888937717e-4 9.699663888937717e-4
      9.699663888937600e-4 9.699663888937717e-4 -9.699663888937717e-4
      -9.699663888937602e-4 -9.699663888937717e-4 -9.699663888937717e-4
      </forces>
  </step>
  <step n_step="17">
    <scf_conv>
      <convergence_achieved>true</convergence_achieved>
      <n_scf_steps>18</n_scf_steps>
      <scf_error>6.656125246310313e-10</scf_error>
    </scf_conv>
    <atomic_structure nat="5" alat="1.263551767203e1">
      <atomic_positions>
        <atom name="Sn" index="1">0.000000000000000e0 0.000000000000000e0 0.000000000000000e0</atom>
        <atom name="I" index="2">2.963305461665474e0 9.890922217471365e0 9.890922217471365e0</atom>
        <atom name="I" index="3">9.890922217471552e0 2.963305461665460e0 9.890922217471365e0</atom>
        <atom name="I" index="4">9.890922217471552e0 9.890922217471365e0 2.963305461665460e0</atom>
        <atom name="I" index="5">2.963305461665474e0 2.963305461665460e0 2.963305461665460e0</atom>
      </atomic_positions>
      <cell>
        <a1>1.285422767913694e1 0.000000000000000e0 0.000000000000000e0</a1>
        <a2>0.000000000000000e0 1.285422767913675e1 0.000000000000000e0</a2>
        <a3>0.000000000000000e0 0.000000000000000e0 1.285422767913675e1</a3>
      </cell>
    </atomic_structure>
    <total_energy>
      <etot>-9.789205303016685e2</etot>
      <eband>-1.301786278585757e1</eband>
      <ehart>4.886911461515144e1</ehart>
      <vtxc>-2.679055522781940e1</vtxc>
      <etxc>-5.548534428222094e1</etxc>
      <ewald>-5.772141600282814e1</ewald>
    </total_energy>
    <forces rank="2" dims="3 5" order="F">
      0.000000000000000e0 0.000000000000000e0 0.000000000000000e0
      -9.315601717467496e-4 9.315601717467631e-4 9.315601717467628e-4
      9.315601717467494e-4 -9.315601717467628e-4 9.315601717467631e-4
      9.315601717467494e-4 9.315601717467628e-4 -9.315601717467631e-4
      -9.315601717467496e-4 -9.315601717467628e-4 -9.315601717467631e-4
      </forces>
  </step>
  <step n_step="18">
    <scf_conv>
      <convergence_achieved>true</convergence_achieved>
      <n_scf_steps>15</n_scf_steps>
      <scf_error>8.165158771169022e-9</scf_error>
    </scf_conv>
    <atomic_structure nat="5" alat="1.263551767203e1">
      <atomic_positions>
        <atom name="Sn" index="1">0.000000000000000e0 0.000000000000000e0 0.000000000000000e0</atom>
        <atom name="I" index="2">2.960093016359357e0 9.953665223992544e0 9.953665223992544e0</atom>
        <atom name="I" index="3">9.953665223992784e0 2.960093016359341e0 9.953665223992544e0</atom>
        <atom name="I" index="4">9.953665223992784e0 9.953665223992544e0 2.960093016359341e0</atom>
        <atom name="I" index="5">2.960093016359357e0 2.960093016359341e0 2.960093016359341e0</atom>
      </atomic_positions>
      <cell>
        <a1>1.291375824035203e1 0.000000000000000e0 0.000000000000000e0</a1>
        <a2>0.000000000000000e0 1.291375824035179e1 0.000000000000000e0</a2>
        <a3>0.000000000000000e0 0.000000000000000e0 1.291375824035179e1</a3>
      </cell>
    </atomic_structure>
    <total_energy>
      <etot>-9.789205692079271e2</etot>
      <eband>-1.314873407847242e1</eband>
      <ehart>4.939845879337305e1</ehart>
      <vtxc>-2.679238102898143e1</vtxc>
      <etxc>-5.548687510846145e1</etxc>
      <ewald>-5.706215817998481e1</ewald>
    </total_energy>
    <forces rank="2" dims="3 5" order="F">
      0.000000000000000e0 0.000000000000000e0 0.000000000000000e0
      -6.392247167537935e-4 6.392247167538056e-4 6.392247167538054e-4
      6.392247167537935e-4 -6.392247167538054e-4 6.392247167538054e-4
      6.392247167537935e-4 6.392247167538056e-4 -6.392247167538056e-4
      -6.392247167537933e-4 -6.392247167538056e-4 -6.392247167538056e-4
      </forces>
  </step>
  <step n_step="19">
    <scf_conv>
      <convergence_achieved>true</convergence_achieved>
      <n_scf_steps>15</n_scf_steps>
      <scf_error>4.106234160612374e-9</scf_error>
    </scf_conv>
    <atomic_structure nat="5" alat="1.263551767203e1">
      <atomic_positions>
        <atom name="Sn" index="1">0.000000000000000e0 0.000000000000000e0 0.000000000000000e0</atom>
        <atom name="I" index="2">2.954100401413471e0 1.004248824753638e1 1.004248824753638e1</atom>
        <atom name="I" index="3">1.004248824753670e1 2.954100401413452e0 1.004248824753638e1</atom>
        <atom name="I" index="4">1.004248824753670e1 1.004248824753638e1 2.954100401413452e0</atom>
        <atom name="I" index="5">2.954100401413471e0 2.954100401413452e0 2.954100401413452e0</atom>
      </atomic_positions>
      <cell>
        <a1>1.299658864895002e1 0.000000000000000e0 0.000000000000000e0</a1>
        <a2>0.000000000000000e0 1.299658864894970e1 0.000000000000000e0</a2>
        <a3>0.000000000000000e0 0.000000000000000e0 1.299658864894970e1</a3>
      </cell>
    </atomic_structure>
    <total_energy>
      <etot>-9.789205784159520e2</etot>
      <eband>-1.332782083862142e1</eband>
      <ehart>5.017035629151646e1</ehart>
      <vtxc>-2.679644417219785e1</vtxc>
      <etxc>-5.549018385897985e1</etxc>
      <ewald>-5.611146894222333e1</ewald>
    </total_energy>
    <forces rank="2" dims="3 5" order="F">
      0.000000000000000e0 0.000000000000000e0 0.000000000000000e0
      -7.246661185116326e-5 7.246661185116508e-5 7.246661185116508e-5
      7.246661185116326e-5 -7.246661185116508e-5 7.246661185116508e-5
      7.246661185116326e-5 7.246661185116508e-5 -7.246661185116508e-5
      -7.246661185116326e-5 -7.246661185116508e-5 -7.246661185116508e-5
      </forces>
  </step>
  <step n_step="20">
    <scf_conv>
      <convergence_achieved>true</convergence_achieved>
      <n_scf_steps>15</n_scf_steps>
      <scf_error>3.671196024511664e-9</scf_error>
    </scf_conv>
    <atomic_structure nat="5" alat="1.263551767203e1">
      <atomic_positions>
        <atom name="Sn" index="1">0.000000000000000e0 0.000000000000000e0 0.000000000000000e0</atom>
        <atom name="I" index="2">2.954809759636110e0 9.997376452480216e0 9.997376452480216e0</atom>
        <atom name="I" index="3">9.997376452480490e0 2.954809759636094e0 9.997376452480216e0</atom>
        <atom name="I" index="4">9.997376452480490e0 9.997376452480216e0 2.954809759636094e0</atom>
        <atom name="I" index="5">2.954809759636110e0 2.954809759636094e0 2.954809759636094e0</atom>
      </atomic_positions>
      <cell>
        <a1>1.295218621211647e1 0.000000000000000e0 0.000000000000000e0</a1>
        <a2>0.000000000000000e0 1.295218621211619e1 0.000000000000000e0</a2>
        <a3>0.000000000000000e0 0.000000000000000e0 1.295218621211619e1</a3>
      </cell>
    </atomic_structure>
    <total_energy>
      <etot>-9.789205903317399e2</etot>
      <eband>-1.323410071848500e1</eband>
      <ehart>4.981390962025501e1</ehart>
      <vtxc>-2.679652536699988e1</vtxc>
      <etxc>-5.549017774518333e1</etxc>
      <ewald>-5.656156666058479e1</ewald>
    </total_energy>
    <forces rank="2" dims="3 5" order="F">
      0.000000000000000e0 0.000000000000000e0 0.000000000000000e0
      -1.396832570201434e-4 1.396832570201465e-4 1.396832570201464e-4
      1.396832570201434e-4 -1.396832570201464e-4 1.396832570201465e-4
      1.396832570201434e-4 1.396832570201465e-4 -1.396832570201464e-4
      -1.396832570201434e-4 -1.396832570201464e-4 -1.396832570201464e-4
      </forces>
  </step>
  <step n_step="21">
    <scf_conv>
      <convergence_achieved>true</convergence_achieved>
      <n_scf_steps>15</n_scf_steps>
      <scf_error>6.175859692730555e-9</scf_error>
    </scf_conv>
    <atomic_structure nat="5" alat="1.263551767203e1">
      <atomic_positions>
        <atom name="Sn" index="1">0.000000000000000e0 0.000000000000000e0 0.000000000000000e0</atom>
        <atom name="I" index="2">2.954211055559574e0 9.931371501306471e0 9.931371501306471e0</atom>
        <atom name="I" index="3">9.931371501306680e0 2.954211055559561e0 9.931371501306471e0</atom>
        <atom name="I" index="4">9.931371501306680e0 9.931371501306471e0 2.954211055559561e0</atom>
        <atom name="I" index="5">2.954211055559574e0 2.954211055559561e0 2.954211055559561e0</atom>
      </atomic_positions>
      <cell>
        <a1>1.288558255686615e1 0.000000000000000e0 0.000000000000000e0</a1>
        <a2>0.000000000000000e0 1.288558255686593e1 0.000000000000000e0</a2>
        <a3>0.000000000000000e0 0.000000000000000e0 1.288558255686593e1</a3>
      </cell>
    </atomic_structure>
    <total_energy>
      <etot>-9.789205929315964e2</etot>
      <eband>-1.309273608631087e1</eband>
      <ehart>4.931739472269102e1</ehart>
      <vtxc>-2.679831534916987e1</vtxc>
      <etxc>-5.549147663201584e1</etxc>
      <ewald>-5.720050435644660e1</ewald>
    </total_energy>
    <forces rank="2" dims="3 5" order="F">
      0.000000000000000e0 0.000000000000000e0 0.000000000000000e0
      -9.037449348342975e-5 9.037449348343129e-5 9.037449348343134e-5
      9.037449348342975e-5 -9.037449348343131e-5 9.037449348343134e-5
      9.037449348342975e-5 9.037449348343129e-5 -9.037449348343131e-5
      -9.037449348342975e-5 -9.037449348343131e-5 -9.037449348343131e-5
      </forces>
  </step>
  <step n_step="22">
    <scf_conv>
      <convergence_achieved>true</convergence_achieved>
      <n_scf_steps>15</n_scf_steps>
      <scf_error>1.756308561126648e-9</scf_error>
    </scf_conv>
    <atomic_structure nat="5" alat="1.263551767203e1">
      <atomic_positions>
        <atom name="Sn" index="1">0.000000000000000e0 0.000000000000000e0 0.000000000000000e0</atom>
        <atom name="I" index="2">2.953691129658310e0 9.959812106783650e0 9.959812106783650e0</atom>
        <atom name="I" index="3">9.959812106783884e0 2.953691129658296e0 9.959812106783650e0</atom>
        <atom name="I" index="4">9.959812106783884e0 9.959812106783650e0 2.953691129658296e0</atom>
        <atom name="I" index="5">2.953691129658310e0 2.953691129658296e0 2.953691129658296e0</atom>
      </atomic_positions>
      <cell>
        <a1>1.291350323644208e1 0.000000000000000e0 0.000000000000000e0</a1>
        <a2>0.000000000000000e0 1.291350323644183e1 0.000000000000000e0</a2>
        <a3>0.000000000000000e0 0.000000000000000e0 1.291350323644183e1</a3>
      </cell>
    </atomic_structure>
    <total_energy>
      <etot>-9.789205951875022e2</etot>
      <eband>-1.315295722270523e1</eband>
      <ehart>4.954365783367206e1</ehart>
      <vtxc>-2.679826050905080e1</vtxc>
      <etxc>-5.549147574514066e1</etxc>
      <ewald>-5.691394825410561e1</ewald>
    </total_energy>
    <forces rank="2" dims="3 5" order="F">
      0.000000000000000e0 0.000000000000000e0 0.000000000000000e0
      -3.655735635477756e-5 3.655735635477827e-5 3.655735635477827e-5
      3.655735635477756e-5 -3.655735635477826e-5 3.655735635477827e-5
      3.655735635477757e-5 3.655735635477827e-5 -3.655735635477827e-5
      -3.655735635477757e-5 -3.655735635477827e-5 -3.655735635477827e-5
      </forces>
  </step>
  <output>
    <convergence_info>
      <scf_conv>
        <convergence_achieved>true</convergence_achieved>
        <n_scf_steps>10</n_scf_steps>
        <scf_error>8.652468608864762e-10</scf_error>
      </scf_conv>
      <opt_conv>
        <convergence_achieved>true</convergence_achieved>
        <n_opt_steps>21</n_opt_steps>
        <grad_norm>2.413704642061877e-4</grad_norm>
      </opt_conv>
    </convergence_info>
    <algorithmic_info>
      <real_space_q>false</real_space_q>
      <real_space_beta>false</real_space_beta>
      <uspp>true</uspp>
      <paw>true</paw>
    </algorithmic_info>
    <atomic_species ntyp="2" pseudo_dir="../../pseudo/">
      <species name="Sn">
        <mass>1.187000000000000e2</mass>
        <pseudo_file>Sn.pbe-dn-kjpaw_psl.1.0.0.UPF</pseudo_file>
      </species>
      <species name="I">
        <mass>1.269000000000000e2</mass>
        <pseudo_file>I.pbe-n-kjpaw_psl.1.0.0.UPF</pseudo_file>
      </species>
    </atomic_species>
    <atomic_structure nat="5" alat="1.263551767203e1">
      <atomic_positions>
        <atom name="Sn" index="1">0.000000000000000e0 0.000000000000000e0 0.000000000000000e0</atom>
        <atom name="I" index="2">2.953691129658310e0 9.959812106783648e0 9.959812106783648e0</atom>
        <atom name="I" index="3">9.959812106783883e0 2.953691129658296e0 9.959812106783648e0</atom>
        <atom name="I" index="4">9.959812106783883e0 9.959812106783648e0 2.953691129658296e0</atom>
        <atom name="I" index="5">2.953691129658310e0 2.953691129658296e0 2.953691129658296e0</atom>
      </atomic_positions>
      <cell>
        <a1>1.291350323644208e1 0.000000000000000e0 0.000000000000000e0</a1>
        <a2>0.000000000000000e0 1.291350323644183e1 0.000000000000000e0</a2>
        <a3>0.000000000000000e0 0.000000000000000e0 1.291350323644183e1</a3>
      </cell>
    </atomic_structure>
    <symmetries>
      <nsym>24</nsym>
      <nrot>48</nrot>
      <space_group>0</space_group>
      <symmetry>
        <info name="identity" class="not found">crystal_symmetry</info>
        <rotation rank="2" dims="3 3" order="F">
          1.000000000000000e0 0.000000000000000e0 0.000000000000000e0
          0.000000000000000e0 1.000000000000000e0 0.000000000000000e0
          0.000000000000000e0 0.000000000000000e0 1.000000000000000e0
          </rotation>
        <fractional_translation>0.000000000000000e0 0.000000000000000e0 0.000000000000000e0</fractional_translation>
        <equivalent_atoms nat="5" size="5">
          1 2 3 4 5
          </equivalent_atoms>
      </symmetry>
      <symmetry>
        <info name="180 deg rotation - cart. axis [0,0,1]" class="not found">crystal_symmetry</info>
        <rotation rank="2" dims="3 3" order="F">
          -1.000000000000000e0 0.000000000000000e0 0.000000000000000e0
          0.000000000000000e0 -1.000000000000000e0 0.000000000000000e0
          0.000000000000000e0 0.000000000000000e0 1.000000000000000e0
          </rotation>
        <fractional_translation>0.000000000000000e0 0.000000000000000e0 0.000000000000000e0</fractional_translation>
        <equivalent_atoms nat="5" size="5">
          1 3 2 5 4
          </equivalent_atoms>
      </symmetry>
      <symmetry>
        <info name="180 deg rotation - cart. axis [0,1,0]" class="not found">crystal_symmetry</info>
        <rotation rank="2" dims="3 3" order="F">
          -1.000000000000000e0 0.000000000000000e0 0.000000000000000e0
          0.000000000000000e0 1.000000000000000e0 0.000000000000000e0
          0.000000000000000e0 0.000000000000000e0 -1.000000000000000e0
          </rotation>
        <fractional_translation>0.000000000000000e0 0.000000000000000e0 0.000000000000000e0</fractional_translation>
        <equivalent_atoms nat="5" size="5">
          1 4 5 2 3
          </equivalent_atoms>
      </symmetry>
      <symmetry>
        <info name="180 deg rotation - cart. axis [1,0,0]" class="not found">crystal_symmetry</info>
        <rotation rank="2" dims="3 3" order="F">
          1.000000000000000e0 0.000000000000000e0 0.000000000000000e0
          0.000000000000000e0 -1.000000000000000e0 0.000000000000000e0
          0.000000000000000e0 0.000000000000000e0 -1.000000000000000e0
          </rotation>
        <fractional_translation>0.000000000000000e0 0.000000000000000e0 0.000000000000000e0</fractional_translation>
        <equivalent_atoms nat="5" size="5">
          1 5 4 3 2
          </equivalent_atoms>
      </symmetry>
      <symmetry>
        <info name="120 deg rotation - cart. axis [-1,-1,-1]" class="not found">crystal_symmetry</info>
        <rotation rank="2" dims="3 3" order="F">
          0.000000000000000e0 1.000000000000000e0 0.000000000000000e0
          0.000000000000000e0 0.000000000000000e0 1.000000000000000e0
          1.000000000000000e0 0.000000000000000e0 0.000000000000000e0
          </rotation>
        <fractional_translation>0.000000000000000e0 0.000000000000000e0 0.000000000000000e0</fractional_translation>
        <equivalent_atoms nat="5" size="5">
          1 4 2 3 5
          </equivalent_atoms>
      </symmetry>
      <symmetry>
        <info name="120 deg rotation - cart. axis [-1,1,1]" class="not found">crystal_symmetry</info>
        <rotation rank="2" dims="3 3" order="F">
          0.000000000000000e0 -1.000000000000000e0 0.000000000000000e0
          0.000000000000000e0 0.000000000000000e0 1.000000000000000e0
          -1.000000000000000e0 0.000000000000000e0 0.000000000000000e0
          </rotation>
        <fractional_translation>0.000000000000000e0 0.000000000000000e0 0.000000000000000e0</fractional_translation>
        <equivalent_atoms nat="5" size="5">
          1 2 4 5 3
          </equivalent_atoms>
      </symmetry>
      <symmetry>
        <info name="120 deg rotation - cart. axis [1,1,-1]" class="not found">crystal_symmetry</info>
        <rotation rank="2" dims="3 3" order="F">
          0.000000000000000e0 1.000000000000000e0 0.000000000000000e0
          0.000000000000000e0 0.000000000000000e0 -1.000000000000000e0
          -1.000000000000000e0 0.000000000000000e0 0.000000000000000e0
          </rotation>
        <fractional_translation>0.000000000000000e0 0.000000000000000e0 0.000000000000000e0</fractional_translation>
        <equivalent_atoms nat="5" size="5">
          1 3 5 4 2
          </equivalent_atoms>
      </symmetry>
      <symmetry>
        <info name="120 deg rotation - cart. axis [1,-1,1]" class="not found">crystal_symmetry</info>
        <rotation rank="2" dims="3 3" order="F">
          0.000000000000000e0 -1.000000000000000e0 0.000000000000000e0
          0.000000000000000e0 0.000000000000000e0 -1.000000000000000e0
          1.000000000000000e0 0.000000000000000e0 0.000000000000000e0
          </rotation>
        <fractional_translation>0.000000000000000e0 0.000000000000000e0 0.000000000000000e0</fractional_translation>
        <equivalent_atoms nat="5" size="5">
          1 5 3 2 4
          </equivalent_atoms>
      </symmetry>
      <symmetry>
        <info name="120 deg rotation - cart. axis [1,1,1]" class="not found">crystal_symmetry</info>
        <rotation rank="2" dims="3 3" order="F">
          0.000000000000000e0 0.000000000000000e0 1.000000000000000e0
          1.000000000000000e0 0.000000000000000e0 0.000000000000000e0
          0.000000000000000e0 1.000000000000000e0 0.000000000000000e0
          </rotation>
        <fractional_translation>0.000000000000000e0 0.000000000000000e0 0.000000000000000e0</fractional_translation>
        <equivalent_atoms nat="5" size="5">
          1 3 4 2 5
          </equivalent_atoms>
      </symmetry>
      <symmetry>
        <info name="120 deg rotation - cart. axis [-1,1,-1]" class="not found">crystal_symmetry</info>
        <rotation rank="2" dims="3 3" order="F">
          0.000000000000000e0 0.000000000000000e0 1.000000000000000e0
          -1.000000000000000e0 0.000000000000000e0 0.000000000000000e0
          0.000000000000000e0 -1.000000000000000e0 0.000000000000000e0
          </rotation>
        <fractional_translation>0.000000000000000e0 0.000000000000000e0 0.000000000000000e0</fractional_translation>
        <equivalent_atoms nat="5" size="5">
          1 4 3 5 2
          </equivalent_atoms>
      </symmetry>
      <symmetry>
        <info name="120 deg rotation - cart. axis [1,-1,-1]" class="not found">crystal_symmetry</info>
        <rotation rank="2" dims="3 3" order="F">
          0.000000000000000e0 0.000000000000000e0 -1.000000000000000e0
          -1.000000000000000e0 0.000000000000000e0 0.000000000000000e0
          0.000000000000000e0 1.000000000000000e0 0.000000000000000e0
          </rotation>
        <fractional_translation>0.000000000000000e0 0.000000000000000e0 0.000000000000000e0</fractional_translation>
        <equivalent_atoms nat="5" size="5">
          1 2 5 3 4
          </equivalent_atoms>
      </symmetry>
      <symmetry>
        <info name="120 deg rotation - cart. axis [-1,-1,1]" class="not found">crystal_symmetry</info>
        <rotation rank="2" dims="3 3" order="F">
          0.000000000000000e0 0.000000000000000e0 -1.000000000000000e0
          1.000000000000000e0 0.000000000000000e0 0.000000000000000e0
          0.000000000000000e0 -1.000000000000000e0 0.000000000000000e0
          </rotation>
        <fractional_translation>0.000000000000000e0 0.000000000000000e0 0.000000000000000e0</fractional_translation>
        <equivalent_atoms nat="5" size="5">
          1 5 2 4 3
          </equivalent_atoms>
      </symmetry>
      <symmetry>
        <info name="inv. 180 deg rotation - cart. axis [1,1,0]" class="not found">crystal_symmetry</info>
        <rotation rank="2" dims="3 3" order="F">
          0.000000000000000e0 -1.000000000000000e0 0.000000000000000e0
          -1.000000000000000e0 0.000000000000000e0 0.000000000000000e0
          0.000000000000000e0 0.000000000000000e0 1.000000000000000e0
          </rotation>
        <fractional_translation>0.000000000000000e0 0.000000000000000e0 0.000000000000000e0</fractional_translation>
        <equivalent_atoms nat="5" size="5">
          1 2 3 5 4
          </equivalent_atoms>
      </symmetry>
      <symmetry>
        <info name="inv. 180 deg rotation - cart. axis [1,-1,0]" class="not found">crystal_symmetry</info>
        <rotation rank="2" dims="3 3" order="F">
          0.000000000000000e0 1.000000000000000e0 0.000000000000000e0
          1.000000000000000e0 0.000000000000000e0 0.000000000000000e0
          0.000000000000000e0 0.000000000000000e0 1.000000000000000e0
          </rotation>
        <fractional_translation>0.000000000000000e0 0.000000000000000e0 0.000000000000000e0</fractional_translation>
        <equivalent_atoms nat="5" size="5">
          1 3 2 4 5
          </equivalent_atoms>
      </symmetry>
      <symmetry>
        <info name="inv.  90 deg rotation - cart. axis [0,0,-1]" class="not found">crystal_symmetry</info>
        <rotation rank="2" dims="3 3" order="F">
          0.000000000000000e0 -1.000000000000000e0 0.000000000000000e0
          1.000000000000000e0 0.000000000000000e0 0.000000000000000e0
          0.000000000000000e0 0.000000000000000e0 -1.000000000000000e0
          </rotation>
        <fractional_translation>0.000000000000000e0 0.000000000000000e0 0.000000000000000e0</fractional_translation>
        <equivalent_atoms nat="5" size="5">
          1 5 4 2 3
          </equivalent_atoms>
      </symmetry>
      <symmetry>
        <info name="inv.  90 deg rotation - cart. axis [0,0,1]" class="not found">crystal_symmetry</info>
        <rotation rank="2" dims="3 3" order="F">
          0.000000000000000e0 1.000000000000000e0 0.000000000000000e0
          -1.000000000000000e0 0.000000000000000e0 0.000000000000000e0
          0.000000000000000e0 0.000000000000000e0 -1.000000000000000e0
          </rotation>
        <fractional_translation>0.000000000000000e0 0.000000000000000e0 0.000000000000000e0</fractional_translation>
        <equivalent_atoms nat="5" size="5">
          1 4 5 3 2
          </equivalent_atoms>
      </symmetry>
      <symmetry>
        <info name="inv. 180 deg rotation - cart. axis [1,0,1]" class="not found">crystal_symmetry</info>
        <rotation rank="2" dims="3 3" order="F">
          0.000000000000000e0 0.000000000000000e0 -1.000000000000000e0
          0.000000000000000e0 1.000000000000000e0 0.000000000000000e0
          -1.000000000000000e0 0.000000000000000e0 0.000000000000000e0
          </rotation>
        <fractional_translation>0.000000000000000e0 0.000000000000000e0 0.000000000000000e0</fractional_translation>
        <equivalent_atoms nat="5" size="5">
          1 2 5 4 3
          </equivalent_atoms>
      </symmetry>
      <symmetry>
        <info name="inv. 180 deg rotation - cart. axis [-1,0,1]" class="not found">crystal_symmetry</info>
        <rotation rank="2" dims="3 3" order="F">
          0.000000000000000e0 0.000000000000000e0 1.000000000000000e0
          0.000000000000000e0 1.000000000000000e0 0.000000000000000e0
          1.000000000000000e0 0.000000000000000e0 0.000000000000000e0
          </rotation>
        <fractional_translation>0.000000000000000e0 0.000000000000000e0 0.000000000000000e0</fractional_translation>
        <equivalent_atoms nat="5" size="5">
          1 4 3 2 5
          </equivalent_atoms>
      </symmetry>
      <symmetry>
        <info name="inv.  90 deg rotation - cart. axis [0,1,0]" class="not found">crystal_symmetry</info>
        <rotation rank="2" dims="3 3" order="F">
          0.000000000000000e0 0.000000000000000e0 -1.000000000000000e0
          0.000000000000000e0 -1.000000000000000e0 0.000000000000000e0
          1.000000000000000e0 0.000000000000000e0 0.000000000000000e0
          </rotation>
        <fractional_translation>0.000000000000000e0 0.000000000000000e0 0.000000000000000e0</fractional_translation>
        <equivalent_atoms nat="5" size="5">
          1 5 2 3 4
          </equivalent_atoms>
      </symmetry>
      <symmetry>
        <info name="inv.  90 deg rotation - cart. axis [0,-1,0]" class="not found">crystal_symmetry</info>
        <rotation rank="2" dims="3 3" order="F">
          0.000000000000000e0 0.000000000000000e0 1.000000000000000e0
          0.000000000000000e0 -1.000000000000000e0 0.000000000000000e0
          -1.000000000000000e0 0.000000000000000e0 0.000000000000000e0
          </rotation>
        <fractional_translation>0.000000000000000e0 0.000000000000000e0 0.000000000000000e0</fractional_translation>
        <equivalent_atoms nat="5" size="5">
          1 3 4 5 2
          </equivalent_atoms>
      </symmetry>
      <symmetry>
        <info name="inv. 180 deg rotation - cart. axis [0,1,1]" class="not found">crystal_symmetry</info>
        <rotation rank="2" dims="3 3" order="F">
          1.000000000000000e0 0.000000000000000e0 0.000000000000000e0
          0.000000000000000e0 0.000000000000000e0 -1.000000000000000e0
          0.000000000000000e0 -1.000000000000000e0 0.000000000000000e0
          </rotation>
        <fractional_translation>0.000000000000000e0 0.000000000000000e0 0.000000000000000e0</fractional_translation>
        <equivalent_atoms nat="5" size="5">
          1 5 3 4 2
          </equivalent_atoms>
      </symmetry>
      <symmetry>
        <info name="inv. 180 deg rotation - cart. axis [0,1,-1]" class="not found">crystal_symmetry</info>
        <rotation rank="2" dims="3 3" order="F">
          1.000000000000000e0 0.000000000000000e0 0.000000000000000e0
          0.000000000000000e0 0.000000000000000e0 1.000000000000000e0
          0.000000000000000e0 1.000000000000000e0 0.000000000000000e0
          </rotation>
        <fractional_translation>0.000000000000000e0 0.000000000000000e0 0.000000000000000e0</fractional_translation>
        <equivalent_atoms nat="5" size="5">
          1 2 4 3 5
          </equivalent_atoms>
      </symmetry>
      <symmetry>
        <info name="inv.  90 deg rotation - cart. axis [-1,0,0]" class="not found">crystal_symmetry</info>
        <rotation rank="2" dims="3 3" order="F">
          -1.000000000000000e0 0.000000000000000e0 0.000000000000000e0
          0.000000000000000e0 0.000000000000000e0 -1.000000000000000e0
          0.000000000000000e0 1.000000000000000e0 0.000000000000000e0
          </rotation>
        <fractional_translation>0.000000000000000e0 0.000000000000000e0 0.000000000000000e0</fractional_translation>
        <equivalent_atoms nat="5" size="5">
          1 3 5 2 4
          </equivalent_atoms>
      </symmetry>
      <symmetry>
        <info name="inv.  90 deg rotation - cart. axis [1,0,0]" class="not found">crystal_symmetry</info>
        <rotation rank="2" dims="3 3" order="F">
          -1.000000000000000e0 0.000000000000000e0 0.000000000000000e0
          0.000000000000000e0 0.000000000000000e0 1.000000000000000e0
          0.000000000000000e0 -1.000000000000000e0 0.000000000000000e0
          </rotation>
        <fractional_translation>0.000000000000000e0 0.000000000000000e0 0.000000000000000e0</fractional_translation>
        <equivalent_atoms nat="5" size="5">
          1 4 2 5 3
          </equivalent_atoms>
      </symmetry>
      <symmetry>
        <info name="inversion" class="not found">lattice_symmetry</info>
        <rotation rank="2" dims="3 3" order="F">
          -1.000000000000000e0 0.000000000000000e0 0.000000000000000e0
          0.000000000000000e0 -1.000000000000000e0 0.000000000000000e0
          0.000000000000000e0 0.000000000000000e0 -1.000000000000000e0
          </rotation>
      </symmetry>
      <symmetry>
        <info name="inv. 180 deg rotation - cart. axis [0,0,1]" class="not found">lattice_symmetry</info>
        <rotation rank="2" dims="3 3" order="F">
          1.000000000000000e0 0.000000000000000e0 0.000000000000000e0
          0.000000000000000e0 1.000000000000000e0 0.000000000000000e0
          0.000000000000000e0 0.000000000000000e0 -1.000000000000000e0
          </rotation>
      </symmetry>
      <symmetry>
        <info name="inv. 180 deg rotation - cart. axis [0,1,0]" class="not found">lattice_symmetry</info>
        <rotation rank="2" dims="3 3" order="F">
          1.000000000000000e0 0.000000000000000e0 0.000000000000000e0
          0.000000000000000e0 -1.000000000000000e0 0.000000000000000e0
          0.000000000000000e0 0.000000000000000e0 1.000000000000000e0
          </rotation>
      </symmetry>
      <symmetry>
        <info name="inv. 180 deg rotation - cart. axis [1,0,0]" class="not found">lattice_symmetry</info>
        <rotation rank="2" dims="3 3" order="F">
          -1.000000000000000e0 0.000000000000000e0 0.000000000000000e0
          0.000000000000000e0 1.000000000000000e0 0.000000000000000e0
          0.000000000000000e0 0.000000000000000e0 1.000000000000000e0
          </rotation>
      </symmetry>
      <symmetry>
        <info name="180 deg rotation - cart. axis [0,1,1]" class="not found">lattice_symmetry</info>
        <rotation rank="2" dims="3 3" order="F">
          -1.000000000000000e0 0.000000000000000e0 0.000000000000000e0
          0.000000000000000e0 0.000000000000000e0 1.000000000000000e0
          0.000000000000000e0 1.000000000000000e0 0.000000000000000e0
          </rotation>
      </symmetry>
      <symmetry>
        <info name="180 deg rotation - cart. axis [0,1,-1]" class="not found">lattice_symmetry</info>
        <rotation rank="2" dims="3 3" order="F">
          -1.000000000000000e0 0.000000000000000e0 0.000000000000000e0
          0.000000000000000e0 0.000000000000000e0 -1.000000000000000e0
          0.000000000000000e0 -1.000000000000000e0 0.000000000000000e0
          </rotation>
      </symmetry>
      <symmetry>
        <info name=" 90 deg rotation - cart. axis [-1,0,0]" class="not found">lattice_symmetry</info>
        <rotation rank="2" dims="3 3" order="F">
          1.000000000000000e0 0.000000000000000e0 0.000000000000000e0
          0.000000000000000e0 0.000000000000000e0 1.000000000000000e0
          0.000000000000000e0 -1.000000000000000e0 0.000000000000000e0
          </rotation>
      </symmetry>
      <symmetry>
        <info name=" 90 deg rotation - cart. axis [1,0,0]" class="not found">lattice_symmetry</info>
        <rotation rank="2" dims="3 3" order="F">
          1.000000000000000e0 0.000000000000000e0 0.000000000000000e0
          0.000000000000000e0 0.000000000000000e0 -1.000000000000000e0
          0.000000000000000e0 1.000000000000000e0 0.000000000000000e0
          </rotation>
      </symmetry>
      <symmetry>
        <info name="180 deg rotation - cart. axis [1,1,0]" class="not found">lattice_symmetry</info>
        <rotation rank="2" dims="3 3" order="F">
          0.000000000000000e0 1.000000000000000e0 0.000000000000000e0
          1.000000000000000e0 0.000000000000000e0 0.000000000000000e0
          0.000000000000000e0 0.000000000000000e0 -1.000000000000000e0
          </rotation>
      </symmetry>
      <symmetry>
        <info name="180 deg rotation - cart. axis [1,-1,0]" class="not found">lattice_symmetry</info>
        <rotation rank="2" dims="3 3" order="F">
          0.000000000000000e0 -1.000000000000000e0 0.000000000000000e0
          -1.000000000000000e0 0.000000000000000e0 0.000000000000000e0
          0.000000000000000e0 0.000000000000000e0 -1.000000000000000e0
          </rotation>
      </symmetry>
      <symmetry>
        <info name=" 90 deg rotation - cart. axis [0,0,-1]" class="not found">lattice_symmetry</info>
        <rotation rank="2" dims="3 3" order="F">
          0.000000000000000e0 1.000000000000000e0 0.000000000000000e0
          -1.000000000000000e0 0.000000000000000e0 0.000000000000000e0
          0.000000000000000e0 0.000000000000000e0 1.000000000000000e0
          </rotation>
      </symmetry>
      <symmetry>
        <info name=" 90 deg rotation - cart. axis [0,0,1]" class="not found">lattice_symmetry</info>
        <rotation rank="2" dims="3 3" order="F">
          0.000000000000000e0 -1.000000000000000e0 0.000000000000000e0
          1.000000000000000e0 0.000000000000000e0 0.000000000000000e0
          0.000000000000000e0 0.000000000000000e0 1.000000000000000e0
          </rotation>
      </symmetry>
      <symmetry>
        <info name="180 deg rotation - cart. axis [1,0,1]" class="not found">lattice_symmetry</info>
        <rotation rank="2" dims="3 3" order="F">
          0.000000000000000e0 0.000000000000000e0 1.000000000000000e0
          0.000000000000000e0 -1.000000000000000e0 0.000000000000000e0
          1.000000000000000e0 0.000000000000000e0 0.000000000000000e0
          </rotation>
      </symmetry>
      <symmetry>
        <info name="180 deg rotation - cart. axis [-1,0,1]" class="not found">lattice_symmetry</info>
        <rotation rank="2" dims="3 3" order="F">
          0.000000000000000e0 0.000000000000000e0 -1.000000000000000e0
          0.000000000000000e0 -1.000000000000000e0 0.000000000000000e0
          -1.000000000000000e0 0.000000000000000e0 0.000000000000000e0
          </rotation>
      </symmetry>
      <symmetry>
        <info name=" 90 deg rotation - cart. axis [0,1,0]" class="not found">lattice_symmetry</info>
        <rotation rank="2" dims="3 3" order="F">
          0.000000000000000e0 0.000000000000000e0 1.000000000000000e0
          0.000000000000000e0 1.000000000000000e0 0.000000000000000e0
          -1.000000000000000e0 0.000000000000000e0 0.000000000000000e0
          </rotation>
      </symmetry>
      <symmetry>
        <info name=" 90 deg rotation - cart. axis [0,-1,0]" class="not found">lattice_symmetry</info>
        <rotation rank="2" dims="3 3" order="F">
          0.000000000000000e0 0.000000000000000e0 -1.000000000000000e0
          0.000000000000000e0 1.000000000000000e0 0.000000000000000e0
          1.000000000000000e0 0.000000000000000e0 0.000000000000000e0
          </rotation>
      </symmetry>
      <symmetry>
        <info name="inv. 120 deg rotation - cart. axis [-1,-1,-1]" class="not found">lattice_symmetry</info>
        <rotation rank="2" dims="3 3" order="F">
          0.000000000000000e0 -1.000000000000000e0 0.000000000000000e0
          0.000000000000000e0 0.000000000000000e0 -1.000000000000000e0
          -1.000000000000000e0 0.000000000000000e0 0.000000000000000e0
          </rotation>
      </symmetry>
      <symmetry>
        <info name="inv. 120 deg rotation - cart. axis [-1,1,1]" class="not found">lattice_symmetry</info>
        <rotation rank="2" dims="3 3" order="F">
          0.000000000000000e0 1.000000000000000e0 0.000000000000000e0
          0.000000000000000e0 0.000000000000000e0 -1.000000000000000e0
          1.000000000000000e0 0.000000000000000e0 0.000000000000000e0
          </rotation>
      </symmetry>
      <symmetry>
        <info name="inv. 120 deg rotation - cart. axis [1,1,-1]" class="not found">lattice_symmetry</info>
        <rotation rank="2" dims="3 3" order="F">
          0.000000000000000e0 -1.000000000000000e0 0.000000000000000e0
          0.000000000000000e0 0.000000000000000e0 1.000000000000000e0
          1.000000000000000e0 0.000000000000000e0 0.000000000000000e0
          </rotation>
      </symmetry>
      <symmetry>
        <info name="inv. 120 deg rotation - cart. axis [1,-1,1]" class="not found">lattice_symmetry</info>
        <rotation rank="2" dims="3 3" order="F">
          0.000000000000000e0 1.000000000000000e0 0.000000000000000e0
          0.000000000000000e0 0.000000000000000e0 1.000000000000000e0
          -1.000000000000000e0 0.000000000000000e0 0.000000000000000e0
          </rotation>
      </symmetry>
      <symmetry>
        <info name="inv. 120 deg rotation - cart. axis [1,1,1]" class="not found">lattice_symmetry</info>
        <rotation rank="2" dims="3 3" order="F">
          0.000000000000000e0 0.000000000000000e0 -1.000000000000000e0
          -1.000000000000000e0 0.000000000000000e0 0.000000000000000e0
          0.000000000000000e0 -1.000000000000000e0 0.000000000000000e0
          </rotation>
      </symmetry>
      <symmetry>
        <info name="inv. 120 deg rotation - cart. axis [-1,1,-1]" class="not found">lattice_symmetry</info>
        <rotation rank="2" dims="3 3" order="F">
          0.000000000000000e0 0.000000000000000e0 -1.000000000000000e0
          1.000000000000000e0 0.000000000000000e0 0.000000000000000e0
          0.000000000000000e0 1.000000000000000e0 0.000000000000000e0
          </rotation>
      </symmetry>
      <symmetry>
        <info name="inv. 120 deg rotation - cart. axis [1,-1,-1]" class="not found">lattice_symmetry</info>
        <rotation rank="2" dims="3 3" order="F">
          0.000000000000000e0 0.000000000000000e0 1.000000000000000e0
          1.000000000000000e0 0.000000000000000e0 0.000000000000000e0
          0.000000000000000e0 -1.000000000000000e0 0.000000000000000e0
          </rotation>
      </symmetry>
      <symmetry>
        <info name="inv. 120 deg rotation - cart. axis [-1,-1,1]" class="not found">lattice_symmetry</info>
        <rotation rank="2" dims="3 3" order="F">
          0.000000000000000e0 0.000000000000000e0 1.000000000000000e0
          -1.000000000000000e0 0.000000000000000e0 0.000000000000000e0
          0.000000000000000e0 1.000000000000000e0 0.000000000000000e0
          </rotation>
      </symmetry>
    </symmetries>
    <basis_set>
      <gamma_only>false</gamma_only>
      <ecutwfc>3.500000000000000e1</ecutwfc>
      <ecutrho>1.400000000000000e2</ecutrho>
      <fft_grid nr1="72" nr2="72" nr3="72"></fft_grid>
      <fft_smooth nr1="72" nr2="72" nr3="72"></fft_smooth>
      <fft_box nr1="72" nr2="72" nr3="72"></fft_box>
      <ngm>170589</ngm>
      <ngms>170589</ngms>
      <npwx>21368</npwx>
      <reciprocal_lattice>
        <b1>9.784732648203192e-1 0.000000000000000e0 0.000000000000000e0</b1>
        <b2>0.000000000000000e0 9.784732648203377e-1 0.000000000000000e0</b2>
        <b3>0.000000000000000e0 0.000000000000000e0 9.784732648203377e-1</b3>
      </reciprocal_lattice>
    </basis_set>
    <dft>
      <functional>PBE</functional>
    </dft>
    <magnetization>
      <lsda>false</lsda>
      <noncolin>false</noncolin>
      <spinorbit>false</spinorbit>
      <total>0.000000000000000e0</total>
      <absolute>0.000000000000000e0</absolute>
    </magnetization>
    <total_energy>
      <etot>-9.789209570406516e2</etot>
      <eband>-1.315305678228776e1</eband>
      <ehart>4.954370006690119e1</ehart>
      <vtxc>-2.679840409169097e1</vtxc>
      <etxc>-5.549154398701680e1</etxc>
      <ewald>-5.691394825296790e1</ewald>
    </total_energy>
    <band_structure>
      <lsda>false</lsda>
      <noncolin>false</noncolin>
      <spinorbit>false</spinorbit>
      <nbnd>23</nbnd>
      <nelec>4.200000000000000e1</nelec>
      <num_of_atomic_wfc>25</num_of_atomic_wfc>
      <wf_collected>true</wf_collected>
      <fermi_energy>-2.064430729273970e-2</fermi_energy>
      <highestOccupiedLevel>-2.064430729273970e-2</highestOccupiedLevel>
      <lowestUnoccupiedLevel>3.922697796814369e-2</lowestUnoccupiedLevel>
      <starting_k_points>
        <monkhorst_pack nk1="4" nk2="4" nk3="4" k1="0" k2="0" k3="0">Monkhorst-Pack</monkhorst_pack>
      </starting_k_points>
      <nks>10</nks>
      <occupations_kind>fixed</occupations_kind>
      <ks_energies>
        <k_point weight="3.125000000000e-2">0.000000000000000e0 0.000000000000000e0 0.000000000000000e0</k_point>
        <npw>21247</npw>
        <eigenvalues size="23">
          -7.982759310767382e-1 -7.982759310767030e-1 -7.982759310765649e-1 -7.962201044804678e-1 -7.962201044803994e-1
          -4.497901898731079e-1 -4.237045346848223e-1 -4.237045346847028e-1 -4.237045346846368e-1 -2.453569075351197e-1
          -1.044606338303203e-1 -1.044606338279846e-1 -1.044606338277658e-1 -6.152556158668934e-2 -6.152556158569177e-2
          -3.192141187872932e-2 -3.192141187872387e-2 -3.192141187869295e-2 -2.704734209396433e-2 -2.704734209327282e-2
          -2.704734209256616e-2 4.036883479143613e-2 1.398687546073484e-1
          </eigenvalues>
        <occupations size="23">
          1.000000000000000e0 1.000000000000000e0 1.000000000000000e0 1.000000000000000e0 1.000000000000000e0
          1.000000000000000e0 1.000000000000000e0 1.000000000000000e0 1.000000000000000e0 1.000000000000000e0
          1.000000000000000e0 1.000000000000000e0 1.000000000000000e0 1.000000000000000e0 1.000000000000000e0
          1.000000000000000e0 1.000000000000000e0 1.000000000000000e0 1.000000000000000e0 1.000000000000000e0
          1.000000000000000e0 0.000000000000000e0 0.000000000000000e0
          </occupations>
      </ks_energies>
      <ks_energies>
        <k_point weight="1.875000000000e-1">0.000000000000000e0 0.000000000000000e0 2.446183162050844e-1</k_point>
        <npw>21302</npw>
        <eigenvalues size="23">
          -7.982774300670686e-1 -7.982770907785348e-1 -7.982770907784360e-1 -7.962221422166545e-1 -7.962207871820100e-1
          -4.490802500791135e-1 -4.246812080312683e-1 -4.236822527329204e-1 -4.236822527328306e-1 -2.445772336215258e-1
          -1.064952008928488e-1 -1.050045196953522e-1 -1.050045196947934e-1 -5.880280282764788e-2 -5.753011057756764e-2
          -3.581326564344645e-2 -3.431130945327708e-2 -3.303386352044310e-2 -3.303386352017012e-2 -2.630036687457849e-2
          -2.630036687446184e-2 4.839010825294218e-2 1.377429057507013e-1
          </eigenvalues>
        <occupations size="23">
          1.000000000000000e0 1.000000000000000e0 1.000000000000000e0 1.000000000000000e0 1.000000000000000e0
          1.000000000000000e0 1.000000000000000e0 1.000000000000000e0 1.000000000000000e0 1.000000000000000e0
          1.000000000000000e0 1.000000000000000e0 1.000000000000000e0 1.000000000000000e0 1.000000000000000e0
          1.000000000000000e0 1.000000000000000e0 1.000000000000000e0 1.000000000000000e0 1.000000000000000e0
          1.000000000000000e0 0.000000000000000e0 0.000000000000000e0
          </occupations>
      </ks_energies>
      <ks_energies>
        <k_point weight="9.375000000000e-2">0.000000000000000e0 0.000000000000000e0 -4.892366324101689e-1</k_point>
        <npw>21362</npw>
        <eigenvalues size="23">
          -7.982789070766570e-1 -7.982789070764209e-1 -7.982782223940075e-1 -7.962228337462065e-1 -7.962226340705126e-1
          -4.483120903347108e-1 -4.257144300175781e-1 -4.236599751879924e-1 -4.236599751878662e-1 -2.437897136406863e-1
          -1.084334031908477e-1 -1.055501445437108e-1 -1.055501445434323e-1 -5.475974102656856e-2 -4.823167304679322e-2
          -4.636748533817125e-2 -4.099628351766347e-2 -3.364708659431291e-2 -3.364708659300941e-2 -2.606356921878686e-2
          -2.606356921865349e-2 5.666791909084905e-2 1.339922755618801e-1
          </eigenvalues>
        <occupations size="23">
          1.000000000000000e0 1.000000000000000e0 1.000000000000000e0 1.000000000000000e0 1.000000000000000e0
          1.000000000000000e0 1.000000000000000e0 1.000000000000000e0 1.000000000000000e0 1.000000000000000e0
          1.000000000000000e0 1.000000000000000e0 1.000000000000000e0 1.000000000000000e0 1.000000000000000e0
          1.000000000000000e0 1.000000000000000e0 1.000000000000000e0 1.000000000000000e0 1.000000000000000e0
          1.000000000000000e0 0.000000000000000e0 0.000000000000000e0
          </occupations>
      </ks_energies>
      <ks_energies>
        <k_point weight="3.750000000000e-1">0.000000000000000e0 2.446183162050844e-1 2.446183162050844e-1</k_point>
        <npw>21320</npw>
        <eigenvalues size="23">
          -7.982786191575321e-1 -7.982777661450521e-1 -7.982771683896640e-1 -7.962222205109787e-1 -7.962212930596183e-1
          -4.484425270400787e-1 -4.246798322788851e-1 -4.244128152115955e-1 -4.237560169911069e-1 -2.441312592957097e-1
          -1.088119108034476e-1 -1.054246948028772e-1 -1.051289434645118e-1 -5.566082808043325e-2 -5.540204949506579e-2
          -4.116363861782500e-2 -3.707150335178194e-2 -3.290488215382804e-2 -3.109660869863395e-2 -2.806885811515378e-2
          -2.413068871571707e-2 5.213555984500335e-2 1.404250108386557e-1
          </eigenvalues>
        <occupations size="23">
          1.000000000000000e0 1.000000000000000e0 1.000000000000000e0 1.000000000000000e0 1.000000000000000e0
          1.000000000000000e0 1.000000000000000e0 1.000000000000000e0 1.000000000000000e0 1.000000000000000e0
          1.000000000000000e0 1.000000000000000e0 1.000000000000000e0 1.000000000000000e0 1.000000000000000e0
          1.000000000000000e0 1.000000000000000e0 1.000000000000000e0 1.000000000000000e0 1.000000000000000e0
          1.000000000000000e0 0.000000000000000e0 0.000000000000000e0
          </occupations>
      </ks_energies>
      <ks_energies>
        <k_point weight="3.750000000000e-1">0.000000000000000e0 2.446183162050844e-1 -4.892366324101689e-1</k_point>
        <npw>21278</npw>
        <eigenvalues size="23">
          -7.982770864577375e-1 -7.982769649966435e-1 -7.982764920246799e-1 -7.962216015387646e-1 -7.962209555726984e-1
          -4.477582412577313e-1 -4.254634718443274e-1 -4.243690076324228e-1 -4.238644399201394e-1 -2.436834008970270e-1
          -1.107420301212870e-1 -1.057370175917228e-1 -1.056051114505862e-1 -5.243206817909155e-2 -5.000249311471433e-2
          -4.792806306980856e-2 -3.984791072823116e-2 -3.253540147824107e-2 -3.200009232069633e-2 -2.794693465912419e-2
          -2.333529654700405e-2 5.640829409762317e-2 1.378097148528953e-1
          </eigenvalues>
        <occupations size="23">
          1.000000000000000e0 1.000000000000000e0 1.000000000000000e0 1.000000000000000e0 1.000000000000000e0
          1.000000000000000e0 1.000000000000000e0 1.000000000000000e0 1.000000000000000e0 1.000000000000000e0
          1.000000000000000e0 1.000000000000000e0 1.000000000000000e0 1.000000000000000e0 1.000000000000000e0
          1.000000000000000e0 1.000000000000000e0 1.000000000000000e0 1.000000000000000e0 1.000000000000000e0
          1.000000000000000e0 0.000000000000000e0 0.000000000000000e0
          </occupations>
      </ks_energies>
      <ks_energies>
        <k_point weight="9.375000000000e-2">0.000000000000000e0 -4.892366324101689e-1 -4.892366324101689e-1</k_point>
        <npw>21296</npw>
        <eigenvalues size="23">
          -7.982778382039058e-1 -7.982772254136008e-1 -7.982772254134125e-1 -7.962227438133258e-1 -7.962209582806443e-1
          -4.471698987149165e-1 -4.251123759931480e-1 -4.251123759930987e-1 -4.241692524109625e-1 -2.435766850100008e-1
          -1.126940535905930e-1 -1.058900882934193e-1 -1.058900882921096e-1 -5.143386897036751e-2 -5.143386897023107e-2
          -4.771169773195060e-2 -3.923922988344544e-2 -3.145663070268317e-2 -3.017685351406575e-2 -3.017685351381382e-2
          -2.064430729273970e-2 5.602112856374593e-2 1.380468097246377e-1
          </eigenvalues>
        <occupations size="23">
          1.000000000000000e0 1.000000000000000e0 1.000000000000000e0 1.000000000000000e0 1.000000000000000e0
          1.000000000000000e0 1.000000000000000e0 1.000000000000000e0 1.000000000000000e0 1.000000000000000e0
          1.000000000000000e0 1.000000000000000e0 1.000000000000000e0 1.000000000000000e0 1.000000000000000e0
          1.000000000000000e0 1.000000000000000e0 1.000000000000000e0 1.000000000000000e0 1.000000000000000e0
          1.000000000000000e0 0.000000000000000e0 0.000000000000000e0
          </occupations>
      </ks_energies>
      <ks_energies>
        <k_point weight="2.500000000000e-1">2.446183162050796e-1 2.446183162050844e-1 2.446183162050844e-1</k_point>
        <npw>21266</npw>
        <eigenvalues size="23">
          -7.982767661211350e-1 -7.982767661209429e-1 -7.982765230779753e-1 -7.962209262142597e-1 -7.962209262141419e-1
          -4.478799731783985e-1 -4.247431609117727e-1 -4.243868686776944e-1 -4.243868686776185e-1 -2.440373062477538e-1
          -1.091478171777689e-1 -1.066076288809382e-1 -1.066076288785532e-1 -5.368380314191085e-2 -5.368380314150844e-2
          -4.434604927046029e-2 -3.559478960606630e-2 -3.559478960550733e-2 -2.736360130646398e-2 -2.554884660245569e-2
          -2.554884660210016e-2 5.149848729295265e-2 1.431837225494185e-1
          </eigenvalues>
        <occupations size="23">
          1.000000000000000e0 1.000000000000000e0 1.000000000000000e0 1.000000000000000e0 1.000000000000000e0
          1.000000000000000e0 1.000000000000000e0 1.000000000000000e0 1.000000000000000e0 1.000000000000000e0
          1.000000000000000e0 1.000000000000000e0 1.000000000000000e0 1.000000000000000e0 1.000000000000000e0
          1.000000000000000e0 1.000000000000000e0 1.000000000000000e0 1.000000000000000e0 1.000000000000000e0
          1.000000000000000e0 0.000000000000000e0 0.000000000000000e0
          </occupations>
      </ks_energies>
      <ks_energies>
        <k_point weight="3.750000000000e-1">2.446183162050796e-1 2.446183162050844e-1 -4.892366324101689e-1</k_point>
        <npw>21300</npw>
        <eigenvalues size="23">
          -7.982780872624476e-1 -7.982772563063429e-1 -7.982771014933270e-1 -7.962217840605801e-1 -7.962215331823304e-1
          -4.472818089898563e-1 -4.253057025618104e-1 -4.245539809817665e-1 -4.243609996770666e-1 -2.439425701948354e-1
          -1.103884748272042e-1 -1.080105837738031e-1 -1.067468401819148e-1 -5.147865191362535e-2 -5.057429651900187e-2
          -4.891164129150731e-2 -3.669613803838846e-2 -3.248805080869028e-2 -2.815053519331918e-2 -2.505501779682062e-2
          -2.436962763674103e-2 5.162376228286614e-2 1.419540484102316e-1
          </eigenvalues>
        <occupations size="23">
          1.000000000000000e0 1.000000000000000e0 1.000000000000000e0 1.000000000000000e0 1.000000000000000e0
          1.000000000000000e0 1.000000000000000e0 1.000000000000000e0 1.000000000000000e0 1.000000000000000e0
          1.000000000000000e0 1.000000000000000e0 1.000000000000000e0 1.000000000000000e0 1.000000000000000e0
          1.000000000000000e0 1.000000000000000e0 1.000000000000000e0 1.000000000000000e0 1.000000000000000e0
          1.000000000000000e0 0.000000000000000e0 0.000000000000000e0
          </occupations>
      </ks_energies>
      <ks_energies>
        <k_point weight="1.875000000000e-1">2.446183162050796e-1 -4.892366324101689e-1 -4.892366324101689e-1</k_point>
        <npw>21336</npw>
        <eigenvalues size="23">
          -7.982783141306089e-1 -7.982783141305017e-1 -7.982782348544561e-1 -7.962226082038786e-1 -7.962224286303079e-1
          -4.467803513930745e-1 -4.250830746955663e-1 -4.250830746954965e-1 -4.246033368111840e-1 -2.441969795433432e-1
          -1.114722196413140e-1 -1.082514695282661e-1 -1.082514695272628e-1 -5.061269024665258e-2 -5.061269024603336e-2
          -4.993525952959066e-2 -3.356623591686234e-2 -3.062741398922920e-2 -2.638207294888184e-2 -2.638207294882174e-2
          -2.146534270387983e-2 4.733814028028263e-2 1.430311543765998e-1
          </eigenvalues>
        <occupations size="23">
          1.000000000000000e0 1.000000000000000e0 1.000000000000000e0 1.000000000000000e0 1.000000000000000e0
          1.000000000000000e0 1.000000000000000e0 1.000000000000000e0 1.000000000000000e0 1.000000000000000e0
          1.000000000000000e0 1.000000000000000e0 1.000000000000000e0 1.000000000000000e0 1.000000000000000e0
          1.000000000000000e0 1.000000000000000e0 1.000000000000000e0 1.000000000000000e0 1.000000000000000e0
          1.000000000000000e0 0.000000000000000e0 0.000000000000000e0
          </occupations>
      </ks_energies>
      <ks_energies>
        <k_point weight="3.125000000000e-2">-4.892366324101592e-1 -4.892366324101689e-1 -4.892366324101689e-1</k_point>
        <npw>21368</npw>
        <eigenvalues size="23">
          -7.982789065708356e-1 -7.982789065707571e-1 -7.982789065706495e-1 -7.962228723575501e-1 -7.962228723574305e-1
          -4.463745081882140e-1 -4.250537850429862e-1 -4.250537850429405e-1 -4.250537850429248e-1 -2.448032126945481e-1
          -1.104048896795610e-1 -1.104048896778762e-1 -1.104048896777557e-1 -5.000452816608467e-2 -5.000452816591703e-2
          -5.000452816316805e-2 -2.960929753069650e-2 -2.960929752949717e-2 -2.247566522110727e-2 -2.247566522108038e-2
          -2.247566522107094e-2 3.922697796814369e-2 1.472796662838196e-1
          </eigenvalues>
        <occupations size="23">
          1.000000000000000e0 1.000000000000000e0 1.000000000000000e0 1.000000000000000e0 1.000000000000000e0
          1.000000000000000e0 1.000000000000000e0 1.000000000000000e0 1.000000000000000e0 1.000000000000000e0
          1.000000000000000e0 1.000000000000000e0 1.000000000000000e0 1.000000000000000e0 1.000000000000000e0
          1.000000000000000e0 1.000000000000000e0 1.000000000000000e0 1.000000000000000e0 1.000000000000000e0
          1.000000000000000e0 0.000000000000000e0 0.000000000000000e0
          </occupations>
      </ks_energies>
    </band_structure>
    <forces rank="2" dims="3 5" order="F">
      0.000000000000000e0 0.000000000000000e0 0.000000000000000e0
      -3.483882562096641e-5 3.483882562096707e-5 3.483882562096707e-5
      3.483882562096641e-5 -3.483882562096707e-5 3.483882562096707e-5
      3.483882562096641e-5 3.483882562096707e-5 -3.483882562096707e-5
      -3.483882562096641e-5 -3.483882562096707e-5 -3.483882562096707e-5
      </forces>
    <stress rank="2" dims="3 3" order="F">
      6.874649390867178e-7 0.000000000000000e0 0.000000000000000e0
      0.000000000000000e0 6.874649390867438e-7 0.000000000000000e0
      0.000000000000000e0 0.000000000000000e0 6.874649390867438e-7
      </stress>
  </output>
  <status>0</status>
  <timing_info>
    <total label="PWSCF">
      <cpu>4.218811275000001e3</cpu>
      <wall>4.341919324874879e3</wall>
    </total>
    <partial label="electrons" calls="23">
      <cpu>3.414834768000000e3</cpu>
      <wall>3.526564709663392e3</wall>
    </partial>
  </timing_info>
  <closed DATE="15 Jan 2021" TIME="16:51:45"></closed>
</qes:espresso>
